Workbook

Sheet Dashboard
F1: 1 | G1: 2 | H1: 3 | I1: 4 | J1: 5 | K1: 6 | L1: 7 | M1: 8 | N1: 9 | O1: 10 | P1: 11 | Q1: 12 | R1: 13 | S1: 14 | T1: 15 | U1: 16 | V1: 17 | W1: 18 | X1: 19 | Y1: 20 | Z1: 21 | AA1: 22 | AB1: 23 | AC1: 24 | AD1: 25 | AE1: 26 | AF1: 27 | AG1: 28 | AH1: 29 | AI1: 30
A2: Billions of Dollars | B2: 2022 | C2: 2023 | D2: 2024 | E2: 2025 | F2: =$E$2+F1&"F" -> 2026F | G2: =$E$2+G1&"F" -> 2027F | H2: =$E$2+H1&"F" -> 2028F | I2: =$E$2+I1&"F" -> 2029F | J2: =$E$2+J1&"F" -> 2030F | K2: =$E$2+K1&"F" -> 2031F | L2: =$E$2+L1&"F" -> 2032F | M2: =$E$2+M1&"F" -> 2033F | ... AI2: =$E$2+AI1&"F" -> 2055F | AJ2: 2056F | AK2: Total | AL2: % Impact (OG GDP) | AM2: % Impact (Change GDP) | AN2: Total after changes
A3: Government revenues | B3: =SUM(B4,B7,B10,B14,B21,B22,B23,B24) -> 4897.399 | C3: =SUM(C4,C7,C10,C14,C21,C22,C23,C24) -> 4440.947 | D3: =SUM(D4,D7,D10,D14,D21,D22,D23,D24) -> 4918.104 | E3: =SUM(E4,E7,E10,E14,E21,E22,E23,E24) -> 5234.315 | F3: =SUM(F4,F7,F10,F14,F21,F22,F23,F24) -> 5386.722 | G3: =SUM(G4,G7,G10,G14,G21,G22,G23,G24) -> 5674.6465 | H3: =SUM(H4,H7,H10,H14,H21,H22,H23,H24) -> 5859.673 | I3: =SUM(I4,I7,I10,I14,I21,I22,I23,I24) -> 6111.06 | ... AJ3: =SUM(AJ4,AJ7,AJ10,AJ14,AJ21,AJ22,AJ23,AJ24) -> 17408.186
A4: Individual Income Taxes | B4: 2632.146 | C4: 2176.481 | D4: 2426.067 | E4: 2656.044 | F4: ='Actual Revenue Progression'!C186 -> 2751.291 | G4: ='Actual Revenue Progression'!D186 -> 2947.025 | H4: ='Actual Revenue Progression'!E186 -> 3044.174 | I4: ='Actual Revenue Progression'!F186 -> 3193.323 | J4: ='Actual Revenue Progression'!G186 -> 3338.979 | K4: ='Actual Revenue Progression'!H186 -> 3461.053 | L4: ='Actual Revenue Progression'!I186 -> 3594.393 | M4: ='Actual Revenue Progression'!J186 -> 3743.854 | ... P4: ='Actual Revenue Progression'!M186 -> 4248.998 | Q4: =P4*1.0409 -> 4422.782 | R4: =Q4*1.0409 -> 4603.6738 | S4: =R4*1.0409 -> 4791.9641 | T4: =S4*1.0409 -> 4987.9554 | U4: =T4*1.0409 -> 5191.9628 | V4: =U4*1.0409 -> 5404.314 | W4: =V4*1.0409 -> 5625.3505 | X4: =W4*1.0409 -> 5855.4273 | Y4: =X4*1.0409 -> 6094.9143 | Z4: =Z64*0.094 -> 6345 | AA4: =Z4*1.04091 -> 6604.5739 | AB4: =AA4*1.04091 -> 6874.7671 | AC4: =AB4*1.04091 -> 7156.0138 | AD4: =AC4*1.04091 -> 7448.7663 | AE4: =AD4*1.04091 -> 7753.4953 | AF4: =AE4*1.04091 -> 8070.6908 | AG4: =AF4*1.04091 -> 8400.8628 | AH4: =AG4*1.04091 -> 8744.5421 | ... AJ4: =AI4*1.04091 -> 9474.6556 | AN4: =AI4+AK5+AK6 -> 22510.714
A5: Income Taxes solution (itemized) | E5: 41.5 | F5: 134.9 | G5: 184.1 | H5: 193.8 | I5: 201.8 | J5: 210.8 | K5: 220.3 | L5: 232 | M5: 241.1 | N5: 249.5 | O5: =N5*1.0444 -> 260.5778 | P5: =O5*1.0444 -> 272.14745 | Q5: =P5*1.0444 -> 284.2308 | R5: =Q5*1.0444 -> 296.85065 | S5: =R5*1.0444 -> 310.03082 | T5: =S5*1.0444 -> 323.79619 | U5: =T5*1.0444 -> 338.17274 | V5: =U5*1.0444 -> 353.18761 | ... AJ5: =AI5*1.0444 -> 648.84586 | AK5: =SUM(E5:AJ5) -> 11303.422 | AL5: =AK5/$AJ$64 -> 0.11811308 | AM5: =AK5/$AJ$68 -> 0.12315201
A6: Include Income from S.corp and LP | E6: 24.5 | F6: 37.1 | G6: 40 | H6: 40.7 | I6: 41.9 | J6: 43.4 | K6: 45.2 | L6: 47 | M6: 48.8 | N6: 51 | O6: =N6*1.034 -> 52.734 | P6: =O6*1.034 -> 54.526956 | Q6: =P6*1.034 -> 56.380873 | R6: =Q6*1.034 -> 58.297822 | S6: =R6*1.034 -> 60.279948 | T6: =S6*1.034 -> 62.329466 | U6: =T6*1.034 -> 64.448668 | V6: =U6*1.034 -> 66.639923 | ... AJ6: =AI6*1.034 -> 106.4197 | AK6: =SUM(E6:AJ6) -> 2105.0109 | AL6: =AK6/$AJ$64 -> 0.021995934 | AM6: =AK6/$AJ$68 -> 0.022934321
A7: Payroll Taxes | B7: 1483.527 | C7: 1614.456 | D7: 1708.926 | E7: 1748.294 | F7: ='Actual Revenue Progression'!C187 -> 1825.573 | G7: ='Actual Revenue Progression'!D187 -> 1896.664 | H7: ='Actual Revenue Progression'!E187 -> 1970.161 | I7: ='Actual Revenue Progression'!F187 -> 2048.466 | J7: ='Actual Revenue Progression'!G187 -> 2131.557 | K7: ='Actual Revenue Progression'!H187 -> 2216.305 | L7: ='Actual Revenue Progression'!I187 -> 2301.556 | M7: ='Actual Revenue Progression'!J187 -> 2388.562 | ... P7: ='Actual Revenue Progression'!M187 -> 2666.066 | Q7: =Q64*0.057 -> 2762.4393 | R7: =R64*0.057 -> 2866.0308 | S7: =S64*0.057 -> 2973.507 | T7: =T64*0.057 -> 3085.0135 | U7: =U64*0.057 -> 3200.7015 | V7: =V64*0.057 -> 3320.7278 | W7: =W64*0.057 -> 3445.2551 | X7: =X64*0.057 -> 3574.4521 | ... AJ7: =AJ64*0.057 -> 5454.9 | AN7: =AI7+AK8+AK9 -> 18517.078
A8: Dividend Tax solution | F8: 118.2 | G8: 122.8 | H8: 127.2 | I8: 131.1 | J8: 135.3 | K8: 278 | L8: 287.7 | M8: 297.5 | N8: 307.4 | O8: =N8*1.037 -> 318.7738 | P8: =O8*1.037 -> 330.56843 | Q8: =P8*1.037 -> 342.79946 | R8: =Q8*1.037 -> 355.48304 | S8: =R8*1.037 -> 368.63592 | T8: =S8*1.037 -> 382.27544 | U8: =T8*1.037 -> 396.41964 | V8: =U8*1.037 -> 411.08716 | ... AJ8: =AI8*1.037 -> 683.65423 | AK8: =SUM(E8:AJ8) -> 12350.487 | AL8: =AK8/$AJ$64 -> 0.1290542 | AM8: =AK8/$AJ$68 -> 0.1345599
A9: Immigration solution | F9: ='Social Security'!$B$22/10 -> 90 | G9: ='Social Security'!$B$22/10 -> 90 | H9: ='Social Security'!$B$22/10 -> 90 | I9: ='Social Security'!$B$22/10 -> 90 | J9: ='Social Security'!$B$22/10 -> 90 | K9: ='Social Security'!$B$22/10 -> 90 | L9: ='Social Security'!$B$22/10 -> 90 | M9: ='Social Security'!$B$22/10 -> 90 | ... O9: ='Social Security'!$B$22/10 -> 90 | AK9: =SUM(E9:AJ9) -> 900 | AL9: =AK9/$AJ$64 -> 0.0094043887 | AM9: =AK9/$AJ$68 -> 0.0098055974
A10: Corporate Income Taxes | B10: 424.865 | C10: 419.584 | D10: 529.867 | E10: 452.089 | F10: ='Actual Revenue Progression'!C188 -> 403.979 | G10: ='Actual Revenue Progression'!D188 -> 419.298 | H10: ='Actual Revenue Progression'!E188 -> 432.534 | I10: ='Actual Revenue Progression'!F188 -> 451.539 | J10: ='Actual Revenue Progression'!G188 -> 477.34 | K10: ='Actual Revenue Progression'!H188 -> 493.465 | L10: ='Actual Revenue Progression'!I188 -> 509.962 | M10: ='Actual Revenue Progression'!J188 -> 525.923 | ... P10: ='Actual Revenue Progression'!M188 -> 575.645 | Q10: =Q64*0.013 -> 630.03002 | R10: =R64*0.013 -> 653.65615 | S10: =S64*0.013 -> 678.16825 | T10: =T64*0.013 -> 703.59956 | U10: =U64*0.013 -> 729.98454 | V10: =V64*0.013 -> 757.35897 | W10: =W64*0.013 -> 785.75993 | X10: =X64*0.013 -> 815.22592 | ... AJ10: =AJ64*0.013 -> 1244.1 | AN10: =AI10+AK11+AK12+AK13 -> 6577.7495 | AQ10: =SUM(AM5:AM25) -> 0.39517476
A11: Halve the GILTI Section 250 Deduction | F11: 60.8 | G11: 64.6 | H11: 65.4 | I11: 65.9 | J11: 68 | K11: =J11*1.0375 -> 70.55 | L11: =K11*1.0375 -> 73.195625 | M11: =L11*1.0375 -> 75.940461 | N11: =M11*1.0375 -> 78.788228 | O11: =N11*1.0375 -> 81.742787 | P11: =O11*1.0375 -> 84.808141 | Q11: =P11*1.0375 -> 87.988447 | R11: =Q11*1.0375 -> 91.288013 | ... Z11: =Y11*1.0375 -> 122.55149 | AA11: =Z11*1.0355 -> 126.90207 | AB11: =AA11*1.0355 -> 131.40709 | AC11: =AB11*1.0355 -> 136.07204 | AD11: =AC11*1.0355 -> 140.9026 | AE11: =AD11*1.0355 -> 145.90464 | AF11: =AE11*1.0355 -> 151.08426 | AG11: =AF11*1.0355 -> 156.44775 | AH11: =AG11*1.0355 -> 162.00165 | ... AJ11: =AI11*1.0355 -> 173.70792 | AK11: =SUM(E11:AJ11) -> 3326.1406 | AL11: =AK11/$AJ$64 -> 0.034755911 | AM11: =AK11/$AJ$68 -> 0.036238662 | AQ11: =SUM(AM31:AM50) -> -0.41578059
A12: Quadruple Stock Buyback Excise Tax | F12: 21 | G12: =F12*1.05 -> 22.05 | H12: =G12*1.05 -> 23.1525 | I12: =H12*1.05 -> 24.310125 | J12: =I12*1.05 -> 25.525631 | K12: =J12*1.05 -> 26.801913 | L12: =K12*1.05 -> 28.142008 | M12: =L12*1.05 -> 29.549109 | N12: =M12*1.05 -> 31.026564 | O12: =N12*1.05 -> 32.577893 | P12: =O12*1.0375 -> 33.799564 | Q12: =P12*1.0375 -> 35.067047 | R12: =Q12*1.0375 -> 36.382061 | S12: =R12*1.0375 -> 37.746389 | T12: =S12*1.0375 -> 39.161878 | U12: =T12*1.0375 -> 40.630449 | V12: =U12*1.0375 -> 42.154091 | W12: =V12*1.0375 -> 43.734869 | ... Z12: =Y12*1.0375 -> 48.841855 | AA12: =Z12*1.0355 -> 50.57574 | AB12: =AA12*1.0355 -> 52.371179 | AC12: =AB12*1.0355 -> 54.230356 | AD12: =AC12*1.0355 -> 56.155534 | AE12: =AD12*1.0355 -> 58.149055 | AF12: =AE12*1.0355 -> 60.213347 | AG12: =AF12*1.0355 -> 62.35092 | AH12: =AG12*1.0355 -> 64.564378 | ... AJ12: =AI12*1.0355 -> 69.229816 | AK12: =SUM(E12:AJ12) -> 1308.8021 | AL12: =AK12/$AJ$64 -> 0.013676093 | AM12: =AK12/$AJ$68 -> 0.01425954
A13: Strengthen Corporate AMT (CAMT) | F13: 11.9 | G13: =F13*1.05 -> 12.495 | H13: =G13*1.05 -> 13.11975 | I13: =H13*1.05 -> 13.775738 | J13: =I13*1.05 -> 14.464524 | K13: =J13*1.05 -> 15.187751 | L13: =K13*1.05 -> 15.947138 | M13: =L13*1.05 -> 16.744495 | N13: =M13*1.05 -> 17.58172 | O13: =N13*1.05 -> 18.460806 | P13: =O13*1.0375 -> 19.153086 | Q13: =P13*1.0375 -> 19.871327 | R13: =Q13*1.0375 -> 20.616501 | S13: =R13*1.0375 -> 21.38962 | T13: =S13*1.0375 -> 22.191731 | U13: =T13*1.0375 -> 23.023921 | V13: =U13*1.0375 -> 23.887318 | W13: =V13*1.0375 -> 24.783092 | ... Z13: =Y13*1.0375 -> 27.677051 | AA13: =Z13*1.0355 -> 28.659586 | AB13: =AA13*1.0355 -> 29.677002 | AC13: =AB13*1.0355 -> 30.730535 | AD13: =AC13*1.0355 -> 31.821469 | AE13: =AD13*1.0355 -> 32.951131 | AF13: =AE13*1.0355 -> 34.120896 | AG13: =AF13*1.0355 -> 35.332188 | AH13: =AG13*1.0355 -> 36.586481 | ... AJ13: =AI13*1.0355 -> 39.230229 | AK13: =SUM(E13:AJ13) -> 741.65452 | AL13: =AK13/$AJ$64 -> 0.007749786 | AM13: =AK13/$AJ$68 -> 0.0080804062
A14: Excise taxes | B14: 87.728 | C14: 75.802 | D14: 101.435 | E14: 105.936 | F14: ='Actual Revenue Progression'!C191 -> 108.344 | G14: ='Actual Revenue Progression'!D191 -> 108.196 | H14: ='Actual Revenue Progression'!E191 -> 106.722 | I14: ='Actual Revenue Progression'!F191 -> 108.028 | J14: ='Actual Revenue Progression'!G191 -> 110.013 | K14: ='Actual Revenue Progression'!H191 -> 109.556 | L14: ='Actual Revenue Progression'!I191 -> 110.831 | M14: ='Actual Revenue Progression'!J191 -> 112.45 | ... P14: ='Actual Revenue Progression'!M191 -> 118.642 | Q14: =(0.009*0.29)*Q64 -> 126.49064 | R14: =(0.009*0.29)*R64 -> 131.23404 | S14: =(0.009*0.29)*S64 -> 136.15532 | T14: =(0.009*0.29)*T64 -> 141.26114 | U14: =(0.009*0.29)*U64 -> 146.55844 | V14: =(0.009*0.29)*V64 -> 152.05438 | W14: =(0.009*0.29)*W64 -> 157.75642 | X14: =(0.009*0.29)*X64 -> 163.67228 | ... Z14: =(0.009*0.29)*Z64 -> 176.175 | AA14: =(0.01*0.29)*AA64 -> 202.69912 | AB14: =(0.01*0.29)*AB64 -> 209.89494 | AC14: =(0.01*0.29)*AC64 -> 217.34621 | AD14: =(0.01*0.29)*AD64 -> 225.06201 | AE14: =(0.01*0.29)*AE64 -> 233.05171 | AF14: =(0.01*0.29)*AF64 -> 241.32504 | AG14: =(0.01*0.29)*AG64 -> 249.89208 | AH14: =(0.01*0.29)*AH64 -> 258.76325 | ... AJ14: =(0.01*0.29)*AJ64 -> 277.53 | AN14: =AI14+SUM(AK15:AK19) -> 2506.3631
A15: OPTION 69 | F15: 6.6 | G15: 8.9 | H15: 9.4 | I15: 9.8 | J15: 10.2 | K15: 10.6 | L15: 11 | M15: 11.5 | N15: 11.9 | O15: 12.4 | P15: 12.8 | Q15: 13.2 | R15: 13.6 | S15: 14 | T15: 14.4 | U15: 14.8 | V15: 15.2 | W15: 15.6 | X15: 16 | Y15: 16.4 | Z15: 16.8 | AA15: 17.2 | AB15: 17.6 | AC15: 18 | AD15: 18.4 | AE15: 18.8 | AF15: 19.2 | AG15: 19.6 | AH15: 20 | AI15: 20.4 | AJ15: 20.4 | AK15: =SUM(E15:AJ15) -> 454.7 | AL15: =AK15/$AJ$64 -> 0.0047513062 | AM15: =AK15/$AJ$68 -> 0.0049540057
A16: OPTION 70 | F16: 3.1 | G16: 4.4 | H16: 4.8 | I16: 5 | J16: 5.3 | K16: 5.5 | L16: 5.8 | M16: 5.9 | N16: 6 | O16: 5.9 | P16: 5.8 | Q16: 5.7 | R16: 5.6 | S16: 5.5 | T16: 5.4 | U16: 5.3 | V16: 5.2 | W16: 5.1 | X16: 5 | Y16: 4.9 | Z16: 4.8 | AA16: 4.7 | AB16: 4.6 | AC16: 4.5 | AD16: 4.4 | AE16: 4.3 | AF16: 4.2 | AG16: 4.1 | AH16: 4 | AI16: 3.9 | AJ16: 3.9 | AK16: =SUM(E16:AJ16) -> 152.6 | AL16: =AK16/$AJ$64 -> 0.0015945664 | AM16: =AK16/$AJ$68 -> 0.0016625935
A17: OPTION 71 | F17: 14.6 | G17: 20.5 | H17: 20.9 | I17: 21.3 | J17: 21.7 | K17: 22.1 | L17: 22.3 | M17: 22.5 | N17: 22.7 | O17: 22.9 | P17: 22.3275 | Q17: 21.755 | R17: 21.1825 | S17: 20.61 | T17: 20.0375 | U17: 19.465 | V17: 18.8925 | W17: 18.32 | X17: 17.7475 | Y17: 17.175 | Z17: 16.6025 | AA17: 16.03 | AB17: 15.4575 | AC17: 14.885 | AD17: 14.3125 | AE17: 13.74 | AF17: 13.1675 | AG17: 12.595 | AH17: 12.0225 | AI17: 11.45 | AJ17: 11.45 | AK17: =SUM(E17:AJ17) -> 560.725 | AL17: =AK17/$AJ$64 -> 0.0058591954 | AM17: =AK17/$AJ$68 -> 0.0061091595
A18: Space | J18: 0.255165 | K18: 0.3317145 | L18: 0.43122885 | M18: 0.56059751 | N18: 0.72877676 | O18: 0.94740978 | P18: 1.2316327 | Q18: 1.6011225 | R18: 2.0814593 | S18: 2.7058971 | T18: 3.5176662 | U18: 4.2211994 | V18: 5.0654393 | W18: 6.0785272 | X18: 7.2942326 | Y18: 8.7530792 | Z18: 10.503695 | AA18: 12.604434 | AB18: 15.125321 | AC18: 18.150385 | AD18: 21.780462 | AE18: 23.958508 | AF18: 26.354359 | AG18: 28.989795 | AH18: 31.888774 | AI18: 35.077652 | AJ18: 35.077652 | AK18: =SUM(E18:AJ18) -> 305.31618 | AL18: =AK18/$AJ$64 -> 0.0031903468 | AM18: =AK18/$AJ$68 -> 0.0033264529
A19: EV | F19: =F87*F88*0.02 -> 1.1362 | G19: =G87*G88*0.02 -> 2.4807845 | H19: =H87*H88*0.02 -> 3.8613523 | I19: =I87*I88*0.02 -> 5.2779034 | J19: =J87*J88*0.02 -> 6.7304379 | K19: =K87*K88*0.02 -> 8.2189557 | L19: =L87*L88*0.02 -> 9.7434569 | M19: =M87*M88*0.02 -> 11.303941 | ... AJ19: =AJ87*AJ88*0.02 -> 0 | AK19: =SUM(E19:AJ19) -> 765.07262 | AL19: =AK19/$AJ$64 -> 0.0079944892 | AM19: =AK19/$AJ$68 -> 0.0083355489
A20: Financial transaction | F20: 10.3 | G20: 25 | H20: 32.7 | I20: 35.9 | J20: 37.6 | K20: 39.1 | L20: 40.6 | M20: 42.2 | N20: 43.8 | O20: =N20*1.05 -> 45.99 | P20: =O20*1.05 -> 48.2895 | Q20: =P20*1.05 -> 50.703975 | R20: =Q20*1.05 -> 53.239174 | S20: =R20*1.05 -> 55.901132 | T20: =S20*1.05 -> 58.696189 | U20: =T20*1.05 -> 61.630999 | V20: =U20*1.05 -> 64.712548 | ... AJ20: =AI20*1.05 -> 128.12642 | AK20: =SUM(E20:AJ20) -> 2078.0548 | AL20: =AK20/$AJ$64 -> 0.021714261 | AM20: =AK20/$AJ$68 -> 0.022640632
A21: Federal Reserve remittances | B21: 106.674 | C21: 0.581 | D21: 3.131 | E21: 5.49 | F21: ='Actual Revenue Progression'!C192 -> 7.853 | G21: ='Actual Revenue Progression'!D192 -> 8.557 | H21: ='Actual Revenue Progression'!E192 -> 9.158 | I21: ='Actual Revenue Progression'!F192 -> 14.822 | J21: ='Actual Revenue Progression'!G192 -> 37.887 | K21: ='Actual Revenue Progression'!H192 -> 93.912 | L21: ='Actual Revenue Progression'!I192 -> 129.707 | M21: ='Actual Revenue Progression'!J192 -> 140.534 | ... P21: ='Actual Revenue Progression'!M192 -> 176.402 | Q21: =(0.009*0.43)*Q64 -> 187.55509 | R21: =(0.009*0.43)*R64 -> 194.58841 | S21: =(0.009*0.43)*S64 -> 201.88547 | T21: =(0.009*0.43)*T64 -> 209.45618 | U21: =(0.009*0.43)*U64 -> 217.31078 | V21: =(0.009*0.43)*V64 -> 225.45994 | W21: =(0.009*0.43)*W64 -> 233.91469 | X21: =(0.009*0.43)*X64 -> 242.68649 | ... Z21: =(0.009*0.43)*Z64 -> 261.225 | AA21: =(0.01*0.43)*AA64 -> 300.55388 | AB21: =(0.01*0.43)*AB64 -> 311.22354 | AC21: =(0.01*0.43)*AC64 -> 322.27197 | AD21: =(0.01*0.43)*AD64 -> 333.71263 | AE21: =(0.01*0.43)*AE64 -> 345.55943 | AF21: =(0.01*0.43)*AF64 -> 357.82679 | AG21: =(0.01*0.43)*AG64 -> 370.52964 | AH21: =(0.01*0.43)*AH64 -> 383.68344 | ... AJ21: =(0.01*0.43)*AJ64 -> 411.51 | AN21: =SUM(AI21,AI23:AI25) -> 638.63401
A22: Customs duties | B22: 99.908 | C22: 80.338 | D22: 77.037 | E22: 195 | F22: ='Actual Revenue Progression'!C189/2 -> 209.194 | G22: ='Actual Revenue Progression'!D189/2 -> 210.5515 | H22: ='Actual Revenue Progression'!E189/2 -> 211.795 | I22: ='Actual Revenue Progression'!F189/2 -> 208.729 | J22: ='Actual Revenue Progression'!G189/2 -> 206.2135 | K22: ='Actual Revenue Progression'!H189/2 -> 202.621 | L22: ='Actual Revenue Progression'!I189/2 -> 194.6535 | M22: ='Actual Revenue Progression'!J189/2 -> 191.1535 | ... P22: ='Actual Revenue Progression'!M189/2 -> 201.178 | Q22: =Q64*0.003 -> 145.39154 | R22: =R64*0.003 -> 150.84373 | S22: =S64*0.003 -> 156.50037 | T22: =T64*0.003 -> 162.36913 | U22: =U64*0.003 -> 168.45797 | V22: =V64*0.003 -> 174.77515 | W22: =W64*0.003 -> 181.32921 | X22: =X64*0.003 -> 188.12906 | ... AJ22: =AJ64*0.003 -> 287.1 | AN22: =AI22 -> 277.18898
A23: Estate and gift taxes | B23: 32.55 | C23: 33.668 | D23: 31.616 | E23: 29.462 | F23: ='Actual Revenue Progression'!C193 -> 36.405 | G23: ='Actual Revenue Progression'!D193 -> 35.207 | H23: ='Actual Revenue Progression'!E193 -> 35.861 | I23: ='Actual Revenue Progression'!F193 -> 35.609 | J23: ='Actual Revenue Progression'!G193 -> 36.166 | K23: ='Actual Revenue Progression'!H193 -> 37.441 | L23: ='Actual Revenue Progression'!I193 -> 39.228 | M23: ='Actual Revenue Progression'!J193 -> 41.391 | ... P23: ='Actual Revenue Progression'!M193 -> 50.675 | Q23: =(0.009*0.12)*Q64 -> 52.340956 | R23: =(0.009*0.12)*R64 -> 54.303741 | S23: =(0.009*0.12)*S64 -> 56.340132 | T23: =(0.009*0.12)*T64 -> 58.452887 | U23: =(0.009*0.12)*U64 -> 60.64487 | V23: =(0.009*0.12)*V64 -> 62.919053 | W23: =(0.009*0.12)*W64 -> 65.278517 | X23: =(0.009*0.12)*X64 -> 67.726461 | ... Z23: =(0.009*0.12)*Z64 -> 72.9 | AA23: =(0.01*0.12)*AA64 -> 83.8755 | AB23: =(0.01*0.12)*AB64 -> 86.85308 | AC23: =(0.01*0.12)*AC64 -> 89.936365 | AD23: =(0.01*0.12)*AD64 -> 93.129106 | AE23: =(0.01*0.12)*AE64 -> 96.435189 | AF23: =(0.01*0.12)*AF64 -> 99.858638 | AG23: =(0.01*0.12)*AG64 -> 103.40362 | AH23: =(0.01*0.12)*AH64 -> 107.07445 | ... AJ23: =(0.01*0.12)*AJ64 -> 114.84
A24: Miscellaneous fees and fines | B24: 30.001 | C24: 40.037 | D24: 40.025 | E24: 42 | F24: ='Actual Revenue Progression'!C194 -> 44.083 | G24: ='Actual Revenue Progression'!D194 -> 49.148 | H24: ='Actual Revenue Progression'!E194 -> 49.268 | I24: ='Actual Revenue Progression'!F194 -> 50.544 | J24: ='Actual Revenue Progression'!G194 -> 50.63 | K24: ='Actual Revenue Progression'!H194 -> 52.519 | L24: ='Actual Revenue Progression'!I194 -> 54.698 | M24: ='Actual Revenue Progression'!J194 -> 56.455 | ... P24: ='Actual Revenue Progression'!M194 -> 61.971 | Q24: =(0.009*0.13)*Q64 -> 56.702702 | R24: =(0.009*0.13)*R64 -> 58.829053 | S24: =(0.009*0.13)*S64 -> 61.035143 | T24: =(0.009*0.13)*T64 -> 63.323961 | U24: =(0.009*0.13)*U64 -> 65.698609 | V24: =(0.009*0.13)*V64 -> 68.162307 | W24: =(0.009*0.13)*W64 -> 70.718393 | X24: =(0.009*0.13)*X64 -> 73.370333 | ... Z24: =(0.009*0.13)*Z64 -> 78.975 | AA24: =(0.01*0.15)*AA64 -> 104.84437 | AB24: =(0.01*0.15)*AB64 -> 108.56635 | AC24: =(0.01*0.15)*AC64 -> 112.42046 | AD24: =(0.01*0.15)*AD64 -> 116.41138 | AE24: =(0.01*0.15)*AE64 -> 120.54399 | AF24: =(0.01*0.15)*AF64 -> 124.8233 | AG24: =(0.01*0.15)*AG64 -> 129.25452 | AH24: =(0.01*0.15)*AH64 -> 133.84306 | ... AJ24: =(0.01*0.15)*AJ64 -> 143.55
A25: Change to CPI-U | F25: -0.1 | G25: -0.1 | H25: -0.1 | I25: -0.2 | J25: -0.2 | K25: -0.2 | L25: -0.8 | M25: -0.9 | N25: -1.1 | O25: =N25*1.1 -> -1.21 | P25: =O25*1.1 -> -1.331 | Q25: =P25*1.1 -> -1.4641 | R25: =Q25*1.1 -> -1.61051 | S25: =R25*1.1 -> -1.771561 | T25: =S25*1.1 -> -1.9487171 | U25: =T25*1.1 -> -2.1435888 | V25: =U25*1.1 -> -2.3579477 | ... AJ25: =AI25*1.1 -> -8.9543024 | AK25: =SUM(F25:AI25) -> -81.143024 | AL25: =AK25/$AJ$64 -> -0.00084788949 | AM25: =AK25/$AJ$68 -> -0.00088406203
A26: https://www.usaspending.gov/
A28: Government Spending | B28: =SUM(B29,B42,B51) -> 6778.258 | C28: =SUM(C29,C42,C51) -> 6479.281 | D28: =SUM(D29,D42,D51) -> 7105.486 | E28: =SUM(E29,E42,E51) -> 7009.775 | F28: =SUM(F29,F42,F51) -> 7450 | G28: =SUM(G29,G42,G51) -> 7773 | H28: =SUM(H29,H42,H51) -> 8151 | I28: =SUM(I29,I42,I51) -> 8339 | ... AJ28: =SUM(AJ29,AJ42,AJ51) -> 24351.347
A29: Mandatory Spending | B29: =SUM(B30,B33,B35,B39,B41) -> 4637.851 | C29: =SUM(C30,C33,C35,C39,C41) -> 4102.875 | D29: =SUM(D30,D33,D35,D39,D41) -> 4415.432 | E29: =SUM(E30,E33,E35,E39,E41) -> 4167.46 | F29: =SUM(F30,F33,F35,F39,F41) -> 4530 | G29: =SUM(G30,G33,G35,G39,G41) -> 4783 | H29: =SUM(H30,H33,H35,H39,H41) -> 5004 | I29: =SUM(I30,I33,I35,I39,I41) -> 5067 | ... AJ29: =SUM(AJ30,AJ33,AJ35,AJ39,AJ41) -> 13821.56
A30: Medicare | B30: 974.649 | C30: 1015.87 | D30: 1043.79 | E30: 1179.972 | F30: ='Gov outlays'!C12 -> 1287 | G30: ='Gov outlays'!D12 -> 1374 | H30: ='Gov outlays'!E12 -> 1533 | I30: ='Gov outlays'!F12 -> 1470 | J30: ='Gov outlays'!G12 -> 1649 | K30: ='Gov outlays'!H12 -> 1753 | L30: ='Gov outlays'!I12 -> 1867 | M30: ='Gov outlays'!J12 -> 2123 | ... P30: ='Gov outlays'!M12 -> 2421 | Q30: =P30*1.0346 -> 2504.7666 | R30: =Q30*1.0346 -> 2591.4315 | S30: =R30*1.0346 -> 2681.0951 | T30: =S30*1.0346 -> 2773.8609 | U30: =T30*1.0346 -> 2869.8365 | V30: =U30*1.0346 -> 2969.1329 | W30: =V30*1.0346 -> 3071.8649 | X30: =W30*1.0346 -> 3178.1514 | Y30: =X30*1.0346 -> 3288.1154 | Z30: =Z$64*(70%*7.2%) -> 3402 | AA30: =Z30*1.0452 -> 3555.7704 | AB30: =AA30*1.0452 -> 3716.4912 | AC30: =AB30*1.0452 -> 3884.4766 | AD30: =AC30*1.0452 -> 4060.055 | AE30: =AD30*1.0452 -> 4243.5695 | AF30: =AE30*1.0452 -> 4435.3788 | AG30: =AF30*1.0452 -> 4635.8579 | AH30: =AG30*1.0452 -> 4845.3987 | ... AJ30: =AI30*1.0452 -> 5293.3221 | AN30: =AI30+AK31+AK32+AI33+AK34 -> -10580.723
A31: Federal Medicare Spending Cap | G31: 0 | H31: -62.650371 | I31: -102.74992 | J31: -149.72295 | K31: -163.55611 | L31: -178.59271 | M31: -194.93368 | N31: -212.68827 | O31: -231.97465 | P31: -252.92064 | Q31: -275.66451 | R31: -300.35579 | S31: -327.15621 | T31: -356.24065 | U31: -387.79819 | V31: -422.03328 | W31: -459.16695 | X31: -499.43814 | Y31: -543.10514 | Z31: -590.4471 | AA31: -641.76577 | AB31: -697.38723 | AC31: -757.66388 | AD31: -822.9765 | AE31: -893.73653 | AF31: -970.38854 | AG31: -1053.4128 | AH31: -1143.3282 | AI31: -1240.6953 | AJ31: -1240.6953 | AK31: =SUM(F31:AJ31) -> -15173.245 | AL31: =AK31/$AJ$64 -> -0.15855011 | AM31: =AK31/$AJ$68 -> -0.16531415
A32: Decrease drug price | F32: -48.540756 | G32: -69.406318 | H32: -83.403712 | I32: -96.701236 | J32: -109.33388 | K32: -102.88941 | L32: -96.767163 | M32: -90.951027 | N32: -85.425698 | O32: -80.176636 | P32: -75.190026 | Q32: -70.452747 | R32: -65.952332 | S32: -61.676937 | T32: -57.615313 | U32: -53.756769 | V32: -50.091153 | W32: -46.608818 | X32: -43.300599 | Y32: -40.157791 | Z32: -37.172124 | AA32: -34.33574 | AB32: -31.641175 | AC32: -29.081339 | AD32: -26.649494 | AE32: -24.339241 | AF32: -22.144502 | AG32: -20.059499 | AH32: -18.078746 | AI32: -16.197031 | AJ32: -16.197031 | AK32: =SUM(F32:AJ32) -> -1704.2942 | AL32: =AK32/$AJ$64 -> -0.017808717 | AM32: =AK32/$AJ$68 -> -0.01856847
A33: Medicaid | B33: 591.949 | C33: 615.772 | D33: 617.517 | E33: 668.134 | F33: ='Gov outlays'!C13 -> 708 | G33: ='Gov outlays'!D13 -> 726 | H33: ='Gov outlays'!E13 -> 746 | I33: ='Gov outlays'!F13 -> 754 | J33: ='Gov outlays'!G13 -> 777 | K33: ='Gov outlays'!H13 -> 804 | L33: ='Gov outlays'!I13 -> 834 | M33: ='Gov outlays'!J13 -> 870 | ... P33: ='Gov outlays'!M13 -> 981 | Q33: =P33*1.0404 -> 1020.6324 | R33: =Q33*1.0404 -> 1061.8659 | S33: =R33*1.0404 -> 1104.7653 | T33: =S33*1.0404 -> 1149.3979 | U33: =T33*1.0404 -> 1195.8335 | V33: =U33*1.0404 -> 1244.1452 | W33: =V33*1.0404 -> 1294.4087 | X33: =W33*1.0404 -> 1346.7028 | Y33: =X33*1.0404 -> 1401.1096 | Z33: =Z$64*(30%*7.2%) -> 1458 | AA33: =Z33*1.0452 -> 1523.9016 | AB33: =AA33*1.0452 -> 1592.782 | AC33: =AB33*1.0452 -> 1664.7757 | AD33: =AC33*1.0452 -> 1740.0236 | AE33: =AD33*1.0452 -> 1818.6726 | AF33: =AE33*1.0452 -> 1900.8766 | AG33: =AF33*1.0452 -> 1986.7962 | AH33: =AG33*1.0452 -> 2076.5994 | ... AJ33: =AI33*1.0452 -> 2268.5666
A34: Change to CPI-U | F34: -0.4 | G34: -0.9 | H34: -1.4 | I34: -1.8 | J34: -2.5 | K34: -3.4 | L34: -6.5 | M34: -5 | N34: -5.6 | O34: =N34*1.2 -> -6.72 | P34: =O34*1.2 -> -8.064 | Q34: =P34*1.2 -> -9.6768 | R34: =Q34*1.2 -> -11.61216 | S34: =R34*1.2 -> -13.934592 | T34: =S34*1.2 -> -16.72151 | U34: =T34*1.2 -> -20.065812 | V34: =U34*1.2 -> -24.078975 | W34: =V34*1.3 -> -31.302667 | X34: =W34*1.3 -> -40.693468 | Y34: =X34*1.06 -> -43.135076 | Z34: =Y34*1.06 -> -45.72318 | AA34: =Z34*1.06 -> -48.466571 | AB34: =AA34*1.06 -> -51.374565 | AC34: =AB34*1.06 -> -54.457039 | AD34: =AC34*1.06 -> -57.724462 | AE34: =AD34*1.06 -> -61.187929 | AF34: =AE34*1.06 -> -64.859205 | ... AJ34: =AI34*1.06 -> -81.883252 | AK34: =SUM(F34:AJ34) -> -938.05618 | AL34: =AK34/$AJ$64 -> -0.0098020499 | AM34: =AK34/$AJ$68 -> -0.010220224
A35: Social Security | B35: 1212.487 | C35: 1347.961 | D35: 1454.382 | E35: 1575.309 | F35: ='Gov outlays'!C11 -> 1666 | G35: ='Gov outlays'!D11 -> 1769 | H35: ='Gov outlays'!E11 -> 1875 | I35: ='Gov outlays'!F11 -> 1979 | J35: ='Gov outlays'!G11 -> 2083 | K35: ='Gov outlays'!H11 -> 2190 | L35: ='Gov outlays'!I11 -> 2298 | M35: ='Gov outlays'!J11 -> 2409 | ... P35: ='Gov outlays'!M11 -> 2747 | Q35: =P35*1.0361 -> 2846.1667 | R35: =Q35*1.0361 -> 2948.9133 | S35: =R35*1.0361 -> 3055.3691 | T35: =S35*1.0361 -> 3165.6679 | U35: =T35*1.0361 -> 3279.9485 | V35: =U35*1.0361 -> 3398.3547 | W35: =V35*1.0361 -> 3521.0353 | X35: =W35*1.0361 -> 3648.1446 | Y35: =X35*1.0361 -> 3779.8427 | Z35: =Z$64*0.058 -> 3915 | AA35: =Z35*1.0373 -> 4061.0295 | AB35: =AA35*1.0373 -> 4212.5059 | AC35: =AB35*1.0373 -> 4369.6324 | AD35: =AC35*1.0373 -> 4532.6197 | AE35: =AD35*1.0373 -> 4701.6864 | AF35: =AE35*1.0373 -> 4877.0593 | AG35: =AF35*1.0373 -> 5058.9736 | AH35: =AG35*1.0373 -> 5247.6733 | ... AJ35: =AI35*1.0373 -> 5646.4508 | AN35: =AI35+AK36+AK37 -> -7646.4718
A36: Reduce SS for high-incomers | G36: -1 | H36: -2 | I36: -5 | J36: -8 | K36: -13 | L36: -20 | M36: -29 | N36: -39 | O36: =N36*1.28 -> -49.92 | P36: =O36*1.28 -> -63.8976 | Q36: =P36*1.28 -> -81.788928 | R36: =Q36*1.28 -> -104.68983 | S36: =R36*1.2 -> -125.62779 | T36: =S36*1.2 -> -150.75335 | U36: =T36*1.2 -> -180.90402 | V36: =U36*1.2 -> -217.08483 | W36: =V36*1.15 -> -249.64755 | X36: =W36*1.15 -> -287.09468 | Y36: =X36*1.15 -> -330.15889 | Z36: =Y36*1.15 -> -379.68272 | AA36: =Z36*1.1 -> -417.65099 | AB36: =AA36*1.1 -> -459.41609 | AC36: =AB36*1.1 -> -505.3577 | AD36: =AC36*1.1 -> -555.89347 | AE36: =AD36*1.07 -> -594.80601 | AF36: =AE36*1.07 -> -636.44243 | AG36: =AF36*1.07 -> -680.9934 | AH36: =AG36*1.07 -> -728.66294 | AI36: =AH36*1.07 -> -779.66935 | AJ36: =AI36*1.07 -> -834.2462 | AK36: =SUM(F36:AJ36) -> -8531.3888 | AL36: =AK36/$AJ$64 -> -0.089147218 | AM36: =AK36/$AJ$68 -> -0.092950404
A37: Change to CPI-U | F37: =-2.9-0.8 -> -3.7 | G37: =-7.2-1.9 -> -9.1 | H37: =-11.8-3.1 -> -14.9 | I37: =-16.6-4.4 -> -21 | J37: =-21.9-5.4 -> -27.3 | K37: =-27.3-6.7 -> -34 | L37: =-33-8 -> -41 | M37: =-38.8-9.4 -> -48.2 | N37: =-44.7-10.8 -> -55.5 | O37: =N37*1.13 -> -62.715 | P37: =O37*1.13 -> -70.86795 | Q37: =P37*1.13 -> -80.080783 | R37: =Q37*1.13 -> -90.491285 | S37: =R37*1.13 -> -102.25515 | T37: =S37*1.13 -> -115.54832 | U37: =T37*1.13 -> -130.5696 | V37: =U37*1.13 -> -147.54365 | W37: =V37*1.13 -> -166.72433 | X37: =W37*1.06 -> -176.72779 | Y37: =X37*1.06 -> -187.33145 | Z37: =Y37*1.06 -> -198.57134 | AA37: =Z37*1.06 -> -210.48562 | AB37: =AA37*1.06 -> -223.11476 | AC37: =AB37*1.06 -> -236.50165 | AD37: =AC37*1.06 -> -250.69174 | AE37: =AD37*1.06 -> -265.73325 | ... AJ37: =AI37*1.06 -> -355.61103 | AK37: =SUM(F37:AJ37) -> -4558.4945 | AL37: =AK37/$AJ$64 -> -0.047633171 | AM37: =AK37/$AJ$68 -> -0.049665291 | AN37: =AL25+AL34+AL37 -> -0.058283111
AN38: =-AM25--AM34--AM37 -> -0.059001452
A39: Other MandaSpending | B39: 1858.766 | C39: 1123.272 | D39: 1299.743 | E39: 1114.045 | F39: ='Gov outlays'!C14 -> 1281 | G39: ='Gov outlays'!D14 -> 1327 | H39: ='Gov outlays'!E14 -> 1284 | I39: ='Gov outlays'!F14 -> 1326 | J39: ='Gov outlays'!G14 -> 1371 | K39: ='Gov outlays'!H14 -> 1377 | L39: ='Gov outlays'!I14 -> 1400 | M39: ='Gov outlays'!J14 -> 1466 | ... P39: ='Gov outlays'!M14 -> 1555 | Q39: =Q$64*0.024 -> 1163.1323 | R39: =R$64*0.024 -> 1206.7498 | S39: =S$64*0.024 -> 1252.0029 | T39: =T$64*0.024 -> 1298.953 | U39: =U$64*0.024 -> 1347.6638 | V39: =V$64*0.024 -> 1398.2012 | W39: =W$64*0.024 -> 1450.6337 | X39: =X$64*0.024 -> 1505.0325 | ... Z39: =Z$64*0.024 -> 1620 | AA39: =AA$64*0.023 -> 1607.6137 | AB39: =AB$64*0.023 -> 1664.684 | AC39: =AC$64*0.023 -> 1723.7803 | AD39: =AD$64*0.023 -> 1784.9745 | AE39: =AE$64*0.023 -> 1848.3411 | AF39: =AF$64*0.023 -> 1913.9572 | AG39: =AG$64*0.023 -> 1981.9027 | AH39: =AH$64*0.023 -> 2052.2603 | ... AJ39: =AJ$64*0.023 -> 2201.1 | AN39: =AI39+AK40 -> -1588.8845
A40: Emergency Spending | AK40: -3714 | AL40: =AK40/$AJ$64 -> -0.038808777 | AM40: =AK40/$AJ$68 -> -0.040464432
A41: Offsetting Receipts | E41: ='Gov outlays'!B15 -> -370 | F41: ='Gov outlays'!C15 -> -412 | G41: ='Gov outlays'!D15 -> -413 | H41: ='Gov outlays'!E15 -> -434 | I41: ='Gov outlays'!F15 -> -462 | J41: ='Gov outlays'!G15 -> -504 | K41: ='Gov outlays'!H15 -> -541 | L41: ='Gov outlays'!I15 -> -564 | ... P41: ='Gov outlays'!M15 -> -675 | Q41: =P41*1.0437 -> -704.4975 | R41: =Q41*1.0437 -> -735.28404 | S41: =R41*1.0437 -> -767.41595 | T41: =S41*1.0437 -> -800.95203 | U41: =T41*1.0437 -> -835.95363 | V41: =U41*1.0437 -> -872.48481 | W41: =V41*1.0437 -> -910.61239 | X41: =W41*1.0437 -> -950.40616 | ... AJ41: =AI41*1.0437 -> -1587.8791
A42: Discretionary Spending | B42: =SUM(B43,B49) -> 1664.52 | C42: =SUM(C43,C49) -> 1718.139 | D42: =SUM(D43,D49) -> 1810.175 | E42: =SUM(E43,E49) -> 1872.377 | F42: =SUM(F43,F49) -> 1881 | G42: =SUM(G43,G49) -> 1882 | H42: =SUM(H43,H49) -> 1929 | I42: =SUM(I43,I49) -> 1948 | ... P42: =SUM(P43,P49) -> 2244 | Q42: =Q$64*0.047 -> 2277.8008 | R42: =R$64*0.047 -> 2363.2184 | S42: =S$64*0.047 -> 2451.8391 | T42: =T$64*0.047 -> 2543.783 | U42: =U$64*0.047 -> 2639.1749 | V42: =V$64*0.047 -> 2738.144 | W42: =W$64*0.047 -> 2840.8243 | X42: =X$64*0.047 -> 2947.3553 | ... Z42: =Z$64*0.047 -> 3172.5 | AA42: =AA$64*0.046 -> 3215.2275 | AB42: =AB$64*0.046 -> 3329.3681 | AC42: =AC$64*0.046 -> 3447.5606 | AD42: =AD$64*0.046 -> 3569.949 | AE42: =AE$64*0.046 -> 3696.6822 | AF42: =AF$64*0.046 -> 3827.9145 | AG42: =AG$64*0.046 -> 3963.8054 | AH42: =AH$64*0.046 -> 4104.5205 | ... AJ42: =AJ$64*0.046 -> 4402.2 | AN42: =AI43+SUM(AK44:AK48) -> -1313.8351
A43: Defense | B43: 752.1 | C43: 806.2 | D43: 850.7 | E43: 892.5 | F43: ='Gov outlays'!C19 -> 885 | G43: ='Gov outlays'!D19 -> 901 | H43: ='Gov outlays'!E19 -> 928 | I43: ='Gov outlays'!F19 -> 938 | J43: ='Gov outlays'!G19 -> 966 | K43: ='Gov outlays'!H19 -> 986 | L43: ='Gov outlays'!I19 -> 1006 | M43: ='Gov outlays'!J19 -> 1034 | ... P43: ='Gov outlays'!M19 -> 1100 | Q43: =Q42*0.49 -> 1116.1224 | R43: =R42*0.49 -> 1157.977 | S43: =S42*0.49 -> 1201.4011 | T43: =T42*0.49 -> 1246.4537 | U43: =U42*0.49 -> 1293.1957 | V43: =V42*0.49 -> 1341.6905 | W43: =W42*0.49 -> 1392.0039 | X43: =X42*0.49 -> 1444.2041 | ... AJ43: =AJ42*0.49 -> 2157.078
A44: OPTION 30 | F44: =-0.2+0.1 -> -0.1 | G44: =-0.7+0.4 -> -0.3 | H44: =-1.3+0.7 -> -0.6 | I44: =-1.9+1 -> -0.9 | J44: =-2.3+1.2 -> -1.1 | K44: =-2.5+1.2 -> -1.3 | L44: =-2.6+1.2 -> -1.4 | M44: =-2.7+1.2 -> -1.5 | N44: =-2.9+1.2 -> -1.7 | O44: -2 | P44: =O44-0.12 -> -2.12 | Q44: =P44-0.12 -> -2.24 | R44: =Q44-0.12 -> -2.36 | S44: =R44-0.12 -> -2.48 | T44: =S44-0.12 -> -2.6 | U44: =T44-0.12 -> -2.72 | V44: =U44-0.12 -> -2.84 | W44: =V44-0.12 -> -2.96 | ... AJ44: =AI44-0.12 -> -4.52 | AK44: =SUM(F44:AJ44) -> -80.62 | AL44: =AK44/$AJ$64 -> -0.00084242424 | AM44: =AK44/$AJ$68 -> -0.00087836362
A45: LRMD | F45: -9.3 | G45: -9.3 | H45: -9.3 | I45: -9.3 | J45: -9.3 | K45: -9.3 | L45: -9.3 | M45: -9.3 | N45: -9.3 | O45: -9.3 | P45: -9.3 | Q45: -9.3 | R45: -9.3 | S45: -9.3 | T45: -9.3 | U45: -9.3 | V45: -9.3 | W45: -9.3 | X45: -9.3 | Y45: -9.3 | Z45: -9.3 | AA45: -9.3 | AB45: -9.3 | AC45: -9.3 | AD45: -9.3 | AE45: -9.3 | AF45: -9.3 | AG45: -9.3 | AH45: -9.3 | AI45: -9.3 | AJ45: -9.3 | AK45: =SUM(F45:AJ45) -> -288.3 | AL45: =AK45/$AJ$64 -> -0.0030125392 | AM45: =AK45/$AJ$68 -> -0.0031410597
A46: Pit | F46: -1.2 | G46: -1.2 | H46: -1.2 | I46: -1.2 | J46: -1.2 | K46: -1.2 | L46: -1.2 | M46: -1.2 | N46: -1.2 | O46: -1.2 | P46: -1.2 | Q46: -1.2 | R46: -1.2 | S46: -1.2 | T46: -1.2 | U46: -1.2 | V46: -1.2 | W46: -1.2 | X46: -1.2 | Y46: -1.2 | Z46: -1.2 | AA46: -1.2 | AB46: -1.2 | AC46: -1.2 | AD46: -1.2 | AE46: -1.2 | AF46: -1.2 | AG46: -1.2 | AH46: -1.2 | AI46: -1.2 | AJ46: -1.2 | AK46: =SUM(F46:AJ46) -> -37.2 | AL46: =AK46/$AJ$64 -> -0.00038871473 | AM46: =AK46/$AJ$68 -> -0.00040529802
A47: OPTION 42 | F47: -13 | G47: -30 | H47: -36 | I47: -39 | J47: -41 | K47: -43 | L47: -44 | M47: -46 | N47: -47 | O47: =N47*1.023 -> -48.081 | P47: =O47*1.023 -> -49.186863 | Q47: =P47*1.023 -> -50.318161 | R47: =Q47*1.023 -> -51.475479 | S47: =R47*1.023 -> -52.659415 | T47: =S47*1.023 -> -53.870581 | U47: =T47*1.023 -> -55.109604 | V47: =U47*1.023 -> -56.377125 | ... AJ47: =AI47*1.023 -> -77.510725 | AK47: =SUM(F47:AJ47) -> -1696.064 | AL47: =AK47/$AJ$64 -> -0.017722717 | AM47: =AK47/$AJ$68 -> -0.018478801
A48: Audit | F48: =-F43*0.17*0.25/1.4 -> -26.866071 | G48: =-G43*0.17*0.25/1.4 -> -27.351786 | H48: =-H43*0.17*0.25/1.4 -> -28.171429 | I48: =-I43*0.17*0.25/1.4 -> -28.475 | J48: =-J43*0.17*0.25/1.4 -> -29.325 | K48: =-K43*0.17*0.25/1.4 -> -29.932143 | L48: =-L43*0.17*0.25/1.4 -> -30.539286 | M48: =-M43*0.17*0.25/1.4 -> -31.389286 | ... AJ48: =-AJ43*0.17*0.25/1.4 -> -65.482725 | AK48: =SUM(F48:AJ48) -> -1294.2643 | AL48: =AK48/$AJ$64 -> -0.013524183 | AM48: =AK48/$AJ$68 -> -0.01410115
A49: Non-defense | B49: 912.42 | C49: 911.939 | D49: 959.475 | E49: 979.877 | F49: ='Gov outlays'!C20 -> 996 | G49: ='Gov outlays'!D20 -> 981 | H49: ='Gov outlays'!E20 -> 1001 | I49: ='Gov outlays'!F20 -> 1010 | J49: ='Gov outlays'!G20 -> 1023 | K49: ='Gov outlays'!H20 -> 1039 | L49: ='Gov outlays'!I20 -> 1057 | M49: ='Gov outlays'!J20 -> 1076 | ... P49: ='Gov outlays'!M20 -> 1144 | Q49: =Q42-Q43 -> 1161.6784 | R49: =R42-R43 -> 1205.2414 | S49: =S42-S43 -> 1250.4379 | T49: =T42-T43 -> 1297.3293 | U49: =U42-U43 -> 1345.9792 | V49: =V42-V43 -> 1396.4534 | W49: =W42-W43 -> 1448.8204 | X49: =X42-X43 -> 1503.1512 | ... AJ49: =AJ42-AJ43 -> 2245.122 | AN49: =AI49+AK50 -> 2021.41
A50: Immigration | F50: =-(65000+150000)*13600/1000000000 -> -2.924 | G50: =F50*1.03 -> -3.01172 | H50: =G50*1.03 -> -3.1020716 | I50: =H50*1.03 -> -3.1951337 | J50: =I50*1.03 -> -3.2909878 | K50: =J50*1.03 -> -3.3897174 | L50: =K50*1.03 -> -3.4914089 | M50: =L50*1.03 -> -3.5961512 | N50: =M50*1.03 -> -3.7040357 | ... AJ50: =AI50*1.03 -> -7.0973155 | AK50: =SUM(F50:AJ50) -> -146.20783 | AL50: =AK50/$AJ$64 -> -0.0015277725 | AM50: =AK50/$AJ$68 -> -0.0015929501
A51: Net interest | B51: 475.887 | C51: 658.267 | D51: 879.879 | E51: 969.938 | F51: ='Gov outlays'!C22 -> 1039 | G51: ='Gov outlays'!D22 -> 1108 | H51: ='Gov outlays'!E22 -> 1218 | I51: ='Gov outlays'!F22 -> 1324 | J51: ='Gov outlays'!G22 -> 1432 | K51: ='Gov outlays'!H22 -> 1548 | L51: ='Gov outlays'!I22 -> 1670 | M51: ='Gov outlays'!J22 -> 1784 | ... P51: ='Gov outlays'!M22 -> 2144 | Q51: =P51*1.0493 -> 2249.6992 | R51: =Q51*1.0493 -> 2360.6094 | S51: =R51*1.0493 -> 2476.9874 | T51: =S51*1.0493 -> 2599.1029 | U51: =T51*1.0493 -> 2727.2387 | V51: =U51*1.0493 -> 2861.6915 | W51: =V51*1.0493 -> 3002.7729 | X51: =W51*1.0493 -> 3150.8096 | Y51: =X51*1.0493 -> 3306.1445 | Z51: =Z64*0.052 -> 3510 | AA51: =Z51*1.0573 -> 3711.123 | AB51: =AA51*1.0573 -> 3923.7703 | AC51: =AB51*1.0573 -> 4148.6024 | AD51: =AC51*1.0573 -> 4386.3173 | AE51: =AD51*1.0573 -> 4637.6533 | AF51: =AE51*1.0573 -> 4903.3908 | AG51: =AF51*1.0573 -> 5184.3551 | AH51: =AG51*1.0573 -> 5481.4187 | ... AJ51: =AI51*1.0573 -> 6127.5863
A52: growth% | C52: =(C51-B51)/B51 -> 0.38324224 | D52: =(D51-C51)/C51 -> 0.33665974 | E52: =(E51-D51)/D51 -> 0.10235385 | F52: =(F51-E51)/E51 -> 0.071202489 | G52: =(G51-F51)/F51 -> 0.06641001 | H52: =(H51-G51)/G51 -> 0.099277978 | I52: =(I51-H51)/H51 -> 0.087027915 | J52: =(J51-I51)/I51 -> 0.081570997 | ... AI52: =(AI51-AH51)/AH51 -> 0.0573 | AK52: =AVERAGE(F52:AJ52) -> 0.061473499
A54: Government Budget (Deficit) | B54: =B3-B28 -> -1880.859 | C54: =C3-C28 -> -2038.334 | D54: =D3-D28 -> -2187.382 | E54: =E3-E28 -> -1775.46 | F54: =F3-F28 -> -2063.278 | G54: =G3-G28 -> -2098.3535 | H54: =H3-H28 -> -2291.327 | I54: =I3-I28 -> -2227.94 | ... AJ54: =AJ3-AJ28 -> -6943.161
A55: growth% | C55: =(C54-B54)/B54 -> 0.083725043 | D55: =(D54-C54)/C54 -> 0.073122462 | E55: =(E54-D54)/D54 -> -0.18831736 | F55: =(F54-E54)/E54 -> 0.16210897 | G55: =(G54-F54)/F54 -> 0.01699989 | H55: =(H54-G54)/G54 -> 0.091964247 | I55: =(I54-H54)/H54 -> -0.027663882 | J55: =(J54-I54)/I54 -> 0.08091533 | ... AJ55: =(AJ54-AI54)/AI54 -> 0.057473169
A56: https://bentleyedu-my.sharepoint.com/:x:/g/personal/adnguyen_falcon_bentley_edu/IQBP6Pdu1naASpx4Ii4QUmr2AXtvrZNHBltqEqZ89AE8JRE?e=HYyq4Q | E56: -1775.46 | F56: =SUM(F3:F25)-SUM(F29:F51) -> -2471.989 | G56: =SUM(G3:G25)-SUM(G29:G51) -> -2339.9114 | H56: =SUM(H3:H25)-SUM(H29:H51) -> -2496.9928 | I56: =SUM(I3:I25)-SUM(I29:I51) -> -2176.6949 | J56: =SUM(J3:J25)-SUM(J29:J51) -> -2333.2804 | K56: =SUM(K3:K25)-SUM(K29:K51) -> -2193.5983 | L56: =SUM(L3:L25)-SUM(L29:L51) -> -2300.093 | M56: =SUM(M3:M25)-SUM(M29:M51) -> -2803.5863 | ... AJ56: =SUM(AJ3:AJ25)-SUM(AJ29:AJ51) -> -3153.9046
A58: Government Debt | B58: ='Gov Debt'!E2/1000 -> 31419.689 | C58: ='Gov Debt'!F2/1000 -> 34001.494 | D58: ='Gov Debt'!G2/1000 -> 36218.605 | E58: ='Gov Debt'!H2/1000 -> 37637.553 | F58: =F60-F54-F61 -> 32305.278 | G58: =G60-G54-G61 -> 34215.353 | H58: =H60-H54-H61 -> 36305.327 | I58: =I60-I54-I61 -> 38310.94 | J58: =J60-J54-J61 -> 40487.215 | K58: =K60-K54-K61 -> 42732.128 | L58: =L60-L54-L61 -> 45115.971 | M58: =M60-M54-M61 -> 47833.677 | ... AJ58: =AJ60-AJ54-AJ61 -> 168688.75
A59: growth% | C59: =(C58-B58)/B58 -> 0.082171564 | D59: =(D58-C58)/C58 -> 0.065206282 | E59: =(E58-D58)/D58 -> 0.039177323 | F59: =(F58-E58)/E58 -> -0.14167433 | G59: =(G58-F58)/F58 -> 0.059125803 | H59: =(H58-G58)/G58 -> 0.061082914 | I59: =(I58-H58)/H58 -> 0.05524294 | J59: =(J58-I58)/I58 -> 0.056805563 | ... AJ59: =(AJ58-AI58)/AI58 -> 0.05774157
A60: Debt held by public initial | E60: ='Gov Debt'!B25 -> 28196 | F60: ='Gov Debt'!C25 -> 30172 | G60: ='Gov Debt'!D25 -> 32095 | H60: ='Gov Debt'!E25 -> 34005 | I60: ='Gov Debt'!F25 -> 36093 | J60: ='Gov Debt'!G25 -> 38103 | K60: ='Gov Debt'!H25 -> 40280 | L60: ='Gov Debt'!I25 -> 42528 | ... P60: ='Gov Debt'!M25 -> 53103 | Q60: =P60*1.0537 -> 55954.631 | R60: =Q60*1.0537 -> 58959.395 | S60: =R60*1.0537 -> 62125.514 | T60: =(T64*1.29)-T61+T54 -> 66422.923 | U60: =T60*1.0572 -> 70222.314 | V60: =U60*1.0572 -> 74239.03 | W60: =V60*1.0572 -> 78485.503 | X60: =W60*1.0572 -> 82974.874 | Y60: =X60*1.0572 -> 87721.036 | Z60: =Y60*1.0572 -> 92738.68 | AA60: =Z60*1.0572 -> 98043.332 | AB60: =AA60*1.0572 -> 103651.41 | ... AJ60: =AI60*1.0572 -> 161745.59
A61: Other means of financing | E61: =-'Gov Debt'!B60 -> -201 | F61: =-'Gov Debt'!C60 -> -70 | G61: =-'Gov Debt'!D60 -> -22 | H61: =-'Gov Debt'!E60 -> -9 | I61: =-'Gov Debt'!F60 -> 10 | J61: =-'Gov Debt'!G60 -> 24 | K61: =-'Gov Debt'!H60 -> 37 | L61: =-'Gov Debt'!I60 -> 45 | ... P61: =-'Gov Debt'!M60 -> 66 | Q61: ='Gov Debt'!N60 -> 77.421053 | R61: ='Gov Debt'!O60 -> 77.421053 | S61: ='Gov Debt'!P60 -> 77.421053 | T61: ='Gov Debt'!Q60 -> 77.421053 | U61: ='Gov Debt'!R60 -> 77.421053 | V61: ='Gov Debt'!S60 -> 77.421053 | W61: ='Gov Debt'!T60 -> 77.421053 | X61: ='Gov Debt'!U60 -> 77.421053 | ... AJ61: ='Gov Debt'!AG60 -> 0
A62: https://www.cbo.gov/data/budget-economic-data | E62: 37637.553 | F62: =F60-F56-F61 -> 32713.989 | G62: =G60-G56-G61 -> 34456.911 | H62: =H60-H56-H61 -> 36510.993 | I62: =I60-I56-I61 -> 38259.695 | J62: =J60-J56-J61 -> 40412.28 | K62: =K60-K56-K61 -> 42436.598 | L62: =L60-L56-L61 -> 44783.093 | M62: =M60-M56-M61 -> 47666.586 | ... AJ62: =AJ60-AJ56-AJ61 -> 164899.5
A64: GDP | B64: =GDP!B28 -> 25565.375 | C64: =GDP!C28 -> 27397.95 | D64: =GDP!D28 -> 28947.9 | E64: =GDP!E28 -> 30330.329 | F64: =GDP!F28 -> 31902.006 | G64: =GDP!G28 -> 33315.187 | H64: =GDP!H28 -> 34665.785 | I64: =GDP!I28 -> 36010.049 | ... P64: =GDP!P28 -> 46712.142 | Q64: =P64*1.0375 -> 48463.848 | R64: =Q64*1.0375 -> 50281.242 | S64: =R64*1.0375 -> 52166.789 | T64: =S64*1.0375 -> 54123.043 | U64: =T64*1.0375 -> 56152.657 | V64: =U64*1.0375 -> 58258.382 | W64: =V64*1.0375 -> 60443.071 | X64: =W64*1.0375 -> 62709.686 | Y64: =X64*1.0375 -> 65061.3 | Z64: 67500 | AA64: =Z64*1.0355 -> 69896.25 | AB64: =AA64*1.0355 -> 72377.567 | AC64: =AB64*1.0355 -> 74946.97 | AD64: =AC64*1.0355 -> 77607.588 | AE64: =AD64*1.0355 -> 80362.657 | AF64: =AE64*1.0355 -> 83215.532 | AG64: =AF64*1.0355 -> 86169.683 | AH64: =AG64*1.0355 -> 89228.707 | AI64: =AH64*1.0355 -> 92396.326 | AJ64: 95700
A65: growth% | C65: =(C64-B64)/B64 -> 0.071681914 | D65: =(D64-C64)/C64 -> 0.056571751 | E65: =(E64-D64)/D64 -> 0.047755758 | F65: =(F64-E64)/E64 -> 0.051818653 | G65: =(G64-F64)/F64 -> 0.044297569 | H65: =(H64-G64)/G64 -> 0.040540001 | I65: =(I64-H64)/H64 -> 0.038777844 | J65: =(J64-I64)/I64 -> 0.038339959 | ... AJ65: =(AJ64-AI64)/AI64 -> 0.035755471
A66: tax changes | F66: =(GDP!B17*(F5+F6))+(GDP!B19*(F8+F9))+(GDP!B18*(F11+F12+F13))+(GDP!B20*F19)+(GDP!B21*(F15+F16+F17+F18))+(GDP!B19+GDP!B17*(F50)) -> 588.71744 | G66: =(GDP!C17*(G5+G6))+(GDP!C19*(G8+G9))+(GDP!C18*(G11+G12+G13))+(GDP!C20*G19)+(GDP!C21*(G15+G16+G17+G18))+(GDP!C19+GDP!C17*(G50)) -> 686.00736 | H66: =(GDP!D17*(H5+H6))+(GDP!D19*(H8+H9))+(GDP!D18*(H11+H12+H13))+(GDP!D20*H19)+(GDP!D21*(H15+H16+H17+H18))+(GDP!D19+GDP!D17*(H50)) -> 711.15942 | I66: =(GDP!E17*(I5+I6))+(GDP!E19*(I8+I9))+(GDP!E18*(I11+I12+I13))+(GDP!E20*I19)+(GDP!E21*(I15+I16+I17+I18))+(GDP!E19+GDP!E17*(I50)) -> 412.22204 | J66: =(GDP!F17*(J5+J6))+(GDP!F19*(J8+J9))+(GDP!F18*(J11+J12+J13))+(GDP!F20*J19)+(GDP!F21*(J15+J16+J17+J18))+(GDP!F19+GDP!F17*(J50)) -> 426.50479 | K66: =(GDP!G17*(K5+K6))+(GDP!G19*(K8+K9))+(GDP!G18*(K11+K12+K13))+(GDP!G20*K19)+(GDP!G21*(K15+K16+K17+K18))+(GDP!G19+GDP!G17*(K50)) -> 552.10213 | L66: =(GDP!H17*(L5+L6))+(GDP!H19*(L8+L9))+(GDP!H18*(L11+L12+L13))+(GDP!H20*L19)+(GDP!H21*(L15+L16+L17+L18))+(GDP!H19+GDP!H17*(L50)) -> 169.75132 | M66: =(GDP!I17*(M5+M6))+(GDP!I19*(M8+M9))+(GDP!I18*(M11+M12+M13))+(GDP!I20*M19)+(GDP!I21*(M15+M16+M17+M18))+(GDP!I19+GDP!I17*(M50)) -> 175.10871 | ... AJ66: =(GDP!AF17*(AJ5+AJ6))+(GDP!AF19*(AJ8+AJ9))+(GDP!AF18*(AJ11+AJ12+AJ13))+(GDP!AF20*AJ19)+(GDP!AF21*(AJ15+AJ16+AJ17+AJ18))+(GDP!AF19+GDP!AF17*(AJ50)) -> 1221.9453
A67: spending changes | F67: =(SUM(F31,F32,F34,F36,F37,F44:F48, F50)*GDP!B16) -> -212.06165 | G67: =(SUM(G31,G32,G34,G36,G37,G44:G48, G50)*GDP!C16) -> -303.13965 | H67: =(SUM(H31,H32,H34,H36,H37,H44:H48, H50)*GDP!D16) -> -485.45517 | I67: =(SUM(I31,I32,I34,I36,I37,I44:I48, I50)*GDP!E16) -> -309.32129 | J67: =(SUM(J31,J32,J34,J36,J37,J44:J48, J50)*GDP!F16) -> -382.07282 | K67: =(SUM(K31,K32,K34,K36,K37,K44:K48, K50)*GDP!G16) -> -404.96739 | L67: =(SUM(L31,L32,L34,L36,L37,L44:L48, L50)*GDP!H16) -> -216.39528 | M67: =(SUM(M31,M32,M34,M36,M37,M44:M48, M50)*GDP!I16) -> -230.53507 | ... AJ67: =(SUM(AJ31,AJ32,AJ34,AJ36,AJ37,AJ44:AJ48, AJ50)*GDP!AF16) -> -2693.7436
A68: GDP after changes | F68: =F64-F66+F67 -> 31101.227 | G68: =G64-G66+G67 -> 32326.04 | H68: =H64-H66+H67 -> 33469.17 | I68: =I64-I66+I67 -> 35288.506 | J68: =J64-J66+J67 -> 36582.095 | K68: =K64-K66+K67 -> 37855.751 | L68: =L64-L66+L67 -> 39890.38 | M68: =M64-M66+M67 -> 41390.287 | ... AJ68: =AJ64-AJ66+AJ67 -> 91784.311
AN69: GOAL | AO69: % TO GOAL
A70: Debt/GDP | B70: =(B58/B64)*100 -> 122.89939 | C70: =(C58/C64)*100 -> 124.10233 | D70: =(D58/D64)*100 -> 125.11652 | E70: =(E58/E64)*100 -> 124.09214 | F70: =(F58/F64)*100 -> 101.2641 | G70: =(G58/G64)*100 -> 102.70197 | H70: =(H58/H64)*100 -> 104.72957 | I70: =(I58/I64)*100 -> 106.38958 | ... AJ70: =(AJ58/AJ64)*100 -> 176.26829 | AK70: =SUM(AK3:AK27)-SUM(AK28:AK51) -> 74432.978 | AL70: =SUM(AL3:AL27)-SUM(AL28:AL51) -> 0.77777407 | AM70: =SUM(AM5:AM25)-SUM(AM31:AM50) -> 0.81095535 | AN70: =-(AJ70-95)/100 -> -0.81268289 | AO70: =AN70+AL70 -> -0.034908822 | AP70: =AN70+AM70 -> -0.0017275388
AM71: =(AJ70/100)-AM70 -> 0.95172754 | AN71: =AN70*AI64 -> -75088.913 | AO71: =AO70*AI64 -> -3225.4469 | AP71: =AP70*AI64 -> -159.61823
D74: defense | E74: OPTION 30 | F74: =-0.2+0.1 -> -0.1 | G74: =-0.7+0.4 -> -0.3 | H74: =-1.3+0.7 -> -0.6 | I74: =-1.9+1 -> -0.9 | J74: =-2.3+1.2 -> -1.1 | K74: =-2.5+1.2 -> -1.3 | L74: =-2.6+1.2 -> -1.4 | M74: =-2.7+1.2 -> -1.5 | N74: =-2.9+1.2 -> -1.7 | O74: -2 | P74: =O74-0.12 -> -2.12 | Q74: =P74-0.12 -> -2.24 | R74: =Q74-0.12 -> -2.36 | S74: =R74-0.12 -> -2.48 | T74: =S74-0.12 -> -2.6 | U74: =T74-0.12 -> -2.72 | V74: =U74-0.12 -> -2.84 | W74: =V74-0.12 -> -2.96 | ... AI74: =AH74-0.12 -> -4.4 | AK74: =SUM(F74:AI74) -> -76.1
E75: OPTION 36 | F75: -0.1 | G75: -0.3 | H75: =-0.8-0.1 -> -0.9 | I75: =-1.2-0.2 -> -1.4 | J75: =-1.7-0.3 -> -2 | K75: =-2.3-0.4 -> -2.7 | L75: =-2.8-0.6 -> -3.4 | M75: =-3.4-0.8 -> -4.2 | N75: =-4-0.8 -> -4.8 | O75: -5 | P75: -5 | Q75: -5 | R75: -5 | S75: -5 | T75: -5 | U75: -5 | V75: -5 | W75: -5 | X75: -5 | Y75: -5 | Z75: -5 | AA75: -5 | AB75: -5 | AC75: -5 | AD75: -5 | AE75: -5 | AF75: -5 | AG75: -5 | AH75: -5 | AI75: -5 | AK75: =SUM(F75:AI75) -> -124.8
E76: LRMD | F76: -9.3 | G76: -9.3 | H76: -9.3 | I76: -9.3 | J76: -9.3 | K76: -9.3 | L76: -9.3 | M76: -9.3 | N76: -9.3 | O76: -9.3 | P76: -9.3 | Q76: -9.3 | R76: -9.3 | S76: -9.3 | T76: -9.3 | U76: -9.3 | V76: -9.3 | W76: -9.3 | X76: -9.3 | Y76: -9.3 | Z76: -9.3 | AA76: -9.3 | AB76: -9.3 | AC76: -9.3 | AD76: -9.3 | AE76: -9.3 | AF76: -9.3 | AG76: -9.3 | AH76: -9.3 | AI76: -9.3 | AK76: =SUM(F76:AI76) -> -279
E77: Pit | F77: -1.2 | G77: -1.2 | H77: -1.2 | I77: -1.2 | J77: -1.2 | K77: -1.2 | L77: -1.2 | M77: -1.2 | N77: -1.2 | O77: -1.2 | P77: -1.2 | Q77: -1.2 | R77: -1.2 | S77: -1.2 | T77: -1.2 | U77: -1.2 | V77: -1.2 | W77: -1.2 | X77: -1.2 | Y77: -1.2 | Z77: -1.2 | AA77: -1.2 | AB77: -1.2 | AC77: -1.2 | AD77: -1.2 | AE77: -1.2 | AF77: -1.2 | AG77: -1.2 | AH77: -1.2 | AI77: -1.2 | AK77: =SUM(F77:AI77) -> -36
E78: OPTION 42 | F78: -13 | G78: -30 | H78: -36 | I78: -39 | J78: -41 | K78: -43 | L78: -44 | M78: -46 | N78: -47 | O78: =N78*1.023 -> -48.081 | P78: =O78*1.023 -> -49.186863 | Q78: =P78*1.023 -> -50.318161 | R78: =Q78*1.023 -> -51.475479 | S78: =R78*1.023 -> -52.659415 | T78: =S78*1.023 -> -53.870581 | U78: =T78*1.023 -> -55.109604 | V78: =U78*1.023 -> -56.377125 | ... AI78: =AH78*1.023 -> -75.76806 | AK78: =SUM(F78:AI78) -> -1618.5533
E79: Audit | F79: =-1250*0.17*0.25/1.4 -> -37.946429 | G79: =-1500*0.17*0.25/1.4 -> -45.535714 | H79: =G79*1.04 -> -47.357143 | I79: =H79*1.04 -> -49.251429 | J79: =I79*1.04 -> -51.221486 | K79: =J79*1.04 -> -53.270345 | L79: =K79*1.04 -> -55.401159 | M79: =L79*1.04 -> -57.617205 | N79: =M79*1.04 -> -59.921894 | O79: =N79*1.04 -> -62.318769 | ... AI79: =AH79*1.04 -> -136.5481 | AK79: =SUM(F79:AI79) -> -2449.8041
D81: excise | E81: OPTION 69 | F81: -6.6 | G81: -8.9 | H81: -9.4 | I81: -9.8 | J81: -10.2 | K81: -10.6 | L81: -11 | M81: -11.5 | N81: -11.9 | O81: -12.4 | P81: =O81-0.4 -> -12.8 | Q81: =P81-0.4 -> -13.2 | R81: =Q81-0.4 -> -13.6 | S81: =R81-0.4 -> -14 | T81: =S81-0.4 -> -14.4 | U81: =T81-0.4 -> -14.8 | V81: =U81-0.4 -> -15.2 | W81: =V81-0.4 -> -15.6 | ... AI81: =AH81-0.4 -> -20.4 | AK81: =SUM(F81:AI81) -> -434.3
E82: OPTION 70 | F82: -3.1 | G82: -4.4 | H82: =-4.7-0.1 -> -4.8 | I82: =-4.9-0.1 -> -5 | J82: =-5.2-0.1 -> -5.3 | K82: =-5.4-0.1 -> -5.5 | L82: =-5.7-0.1 -> -5.8 | M82: =-5.8-0.1 -> -5.9 | N82: =-5.9-0.1 -> -6 | O82: =-5.8-0.1 -> -5.9 | P82: =O82+0.1 -> -5.8 | Q82: =P82+0.1 -> -5.7 | R82: =Q82+0.1 -> -5.6 | S82: =R82+0.1 -> -5.5 | T82: =S82+0.1 -> -5.4 | U82: =T82+0.1 -> -5.3 | V82: =U82+0.1 -> -5.2 | W82: =V82+0.1 -> -5.1 | ... AI82: =AH82+0.1 -> -3.9 | AK82: =SUM(F82:AI82) -> -148.7
E83: OPTION 71 | F83: -14.6 | G83: -20.5 | H83: -20.9 | I83: -21.3 | J83: -21.7 | K83: -22.1 | L83: -22.3 | M83: -22.5 | N83: -22.7 | O83: -22.9 | P83: =O83+0.5725 -> -22.3275 | Q83: =P83+0.5725 -> -21.755 | R83: =Q83+0.5725 -> -21.1825 | S83: =R83+0.5725 -> -20.61 | T83: =S83+0.5725 -> -20.0375 | U83: =T83+0.5725 -> -19.465 | V83: =U83+0.5725 -> -18.8925 | W83: =V83+0.5725 -> -18.32 | ... AI83: =AH83+0.5725 -> -11.45 | AK83: =SUM(F83:AI83) -> -549.275
E84: Space Commercial | F84: 0 | G84: 0 | H84: 0 | I84: 0 | J84: =J85*0.075 -> 0.255165 | K84: =K85*0.075 -> 0.3317145 | L84: =L85*0.075 -> 0.43122885 | M84: =M85*0.075 -> 0.56059751 | N84: =N85*0.075 -> 0.72877676 | O84: =O85*0.075 -> 0.94740978 | P84: =P85*0.075 -> 1.2316327 | Q84: =Q85*0.075 -> 1.6011225 | ... AI84: =AI85*0.075 -> 35.077652 | AK84: =SUM(F84:AI84) -> 270.23853
J85: =3.4022 -> 3.4022 | K85: =J85*1.3 -> 4.42286 | L85: =K85*1.3 -> 5.749718 | M85: =L85*1.3 -> 7.4746334 | N85: =M85*1.3 -> 9.7170234 | O85: =N85*1.3 -> 12.63213 | P85: =O85*1.3 -> 16.42177 | Q85: =P85*1.3 -> 21.3483 | R85: =Q85*1.3 -> 27.752791 | ... T85: =S85*1.3 -> 46.902216 | U85: =T85*1.2 -> 56.282659 | V85: =U85*1.2 -> 67.539191 | W85: =V85*1.2 -> 81.047029 | X85: =W85*1.2 -> 97.256435 | Y85: =X85*1.2 -> 116.70772 | Z85: =Y85*1.2 -> 140.04927 | AA85: =Z85*1.2 -> 168.05912 | AB85: =AA85*1.2 -> 201.67094 | ... AD85: =AC85*1.2 -> 290.40616 | AE85: =AD85*1.1 -> 319.44678 | AF85: =AE85*1.1 -> 351.39145 | AG85: =AF85*1.1 -> 386.5306 | AH85: =AG85*1.1 -> 425.18366 | AI85: =AH85*1.1 -> 467.70202
E86: EV | F86: =-F87*F88*0.02 -> -1.1362 | G86: =-G87*G88*0.02 -> -2.4807845 | H86: =-H87*H88*0.02 -> -3.8613523 | I86: =-I87*I88*0.02 -> -5.2779034 | J86: =-J87*J88*0.02 -> -6.7304379 | K86: =-K87*K88*0.02 -> -8.2189557 | L86: =-L87*L88*0.02 -> -9.7434569 | M86: =-M87*M88*0.02 -> -11.303941 | ... AI86: =-AI87*AI88*0.02 -> -54.738387 | AK86: =SUM(F86:AI86) -> -765.07262
F87: 0.0065 | G87: =F87+0.0075 -> 0.014 | H87: =G87+0.0075 -> 0.0215 | I87: =H87+0.0075 -> 0.029 | J87: =I87+0.0075 -> 0.0365 | K87: =J87+0.0075 -> 0.044 | L87: =K87+0.0075 -> 0.0515 | M87: =L87+0.0075 -> 0.059 | N87: =M87+0.0075 -> 0.0665 | ... AI87: =AH87+0.0075 -> 0.224
F88: 8740 | G88: =F88+119.9444828 -> 8859.9445 | H88: =G88+119.9444828 -> 8979.889 | I88: =H88+119.9444828 -> 9099.8334 | J88: =I88+119.9444828 -> 9219.7779 | K88: =J88+119.9444828 -> 9339.7224 | L88: =K88+119.9444828 -> 9459.6669 | M88: =L88+119.9444828 -> 9579.6114 | N88: =M88+119.9444828 -> 9699.5559 | ... AI88: =AH88+119.9444828 -> 12218.39
E89: Emergency | F89: N/A | G89: N/A | H89: N/A | I89: N/A | J89: N/A | K89: N/A | L89: N/A | M89: N/A | N89: N/A | O89: N/A | P89: N/A | Q89: N/A | R89: N/A | S89: N/A | T89: N/A | U89: N/A | V89: N/A | W89: N/A | X89: N/A | Y89: N/A | Z89: N/A | AA89: N/A | AB89: N/A | AC89: N/A | AD89: N/A | AE89: N/A | AF89: N/A | AG89: N/A | AH89: N/A | AI89: N/A | AK89: =-E109 -> -3713.8794
E90: Immigration | F90: =-(65000+150000)*13600/1000000000 -> -2.924 | G90: =F90*1.03 -> -3.01172 | H90: =G90*1.03 -> -3.1020716 | I90: =H90*1.03 -> -3.1951337 | J90: =I90*1.03 -> -3.2909878 | K90: =J90*1.03 -> -3.3897174 | L90: =K90*1.03 -> -3.4914089 | M90: =L90*1.03 -> -3.5961512 | N90: =M90*1.03 -> -3.7040357 | ... AI90: =AH90*1.03 -> -6.8905975 | AK90: =SUM(F90:AI90) -> -139.11052
E91: H-1B – CBO | F91: EB5 – Past | G91: reduce tax payer and consumer
E92: 2024 | F92: COVID | G92: Pork Barrel | H92: OCO 1st | I92: Border | J92: COVID | K92: DRF Funding | L92: Unspent (2021) | N92: Discretionary | O92: GD + COVID | P92: 2400
E93: 0.05 | F93: 0.626 | G93: 0.0097 | H93: 40 | I93: 3.6 | J93: 403 | K93: 286 | L93: 1600 | O93: MO+DR+Misc | P93: 4100 | Q93: OCO | R93: 2000 | S93: 2100 | X93: =(AI88-F88)/29 -> 119.94448
E94: 0.02 | F94: 0.0072 | G94: 0.001 | H94: 145.9 | J94: 135
E95: 0.03 | F95: 0.07 | G95: 0.0005 | N95: Mandatory | O95: GD | P95: 824
E96: 0.1 | F96: 0.012 | G96: 0.0193 | O96: COVID | P96: 4400
E97: 0.163 | F97: 0.0066 | G97: 0.0227 | O97: Others | P97: =6000-P95-P96 -> 776
E98: 0.25 | G98: 0.0401
E99: 0.328 | G99: 0.0033
E100: 0.45 | G100: 0.000231
E101: 0.25 | G101: 0.035
E102: 0.234 | G102: 0.005
E103: 8 | G103: 0.0276
G104: 0.14
E106: =SUM(E93:E103) -> 9.875 | F106: =SUM(F93:F97) -> 0.7218 | G106: =SUM(G93:G104) -> 0.304431 | H106: =SUM(H93:H94) -> 185.9 | I106: =SUM(I93) -> 3.6 | J106: =SUM(J93:J94) -> 538 | K106: 286
E107: =293+224.9+11.4 -> 529.3 | K107: 381
E109: =E106+L93+I106+R93-H106+G106+K106 -> 3713.8794 | F109: =SUM(P92:P97,H106)-R93-K106-L93-I106-G106-E106 -> 8786.1206 | G109: =SUM(P92:P97) -> 12500
...

Sheet Charts
B2: Individual Income Taxes | C2: 2656.044 | D2: 21755.449
B3: Payroll Taxes | C3: 1748.294 | D3: 17833.424
B4: Corporate Income Taxes | C4: 452.089 | D4: 6295.5815
B5: Excise taxes | C5: 105.936 | D5: 2435.5355
B6: Customs duties | C6: 195 | D6: 230.99081
B7: Others | C7: 77 | D7: 639
B10: Health | C10: 1848.106 | D10: -9241.9477
B11: Social Security | C11: 1575.309 | D11: -6456.6145
B12: Other MandaSpending | C12: 1114.045 | D12: -1588.8845
B13: Defense | C13: 892.5 | D13: -1280.6217
B14: Non-defense | C14: 979.877 | D14: 2028.5073
B51: 2025 | C51: 2026F | D51: 2027F | E51: 2028F | F51: 2029F | G51: 2030F | H51: 2031F | I51: 2032F | J51: 2033F | K51: 2034F | L51: 2035F | M51: 2036F | N51: 2037F | O51: 2038F | P51: 2039F | Q51: 2040F | R51: 2041F | S51: 2042F | T51: 2043F | U51: 2044F | V51: 2045F | W51: 2046F | X51: 2047F | Y51: 2048F | Z51: 2049F | AA51: 2050F | AB51: 2051F | AC51: 2052F | AD51: 2053F | AE51: 2054F | AF51: 2055F | AG51: 2056F
B52: -1775.46 | C52: -2063.278 | D52: -2098.3535 | E52: -2291.327 | F52: -2227.94 | G52: -2408.2145 | H52: -2489.128 | I52: -2632.9715 | J52: -2970.6775 | K52: -3008.873 | L52: -2973.186 | M52: -3317.423 | N52: -2998.2002 | O52: -3109.4852 | P52: -3225.1706 | Q52: -3345.4434 | R52: -3470.4992 | S52: -3600.5422 | T52: -3735.7862 | U52: -3876.4549 | V52: -4022.7819 | W52: -4214.1884 | X52: -4230.1121 | Y52: -4473.1752 | Z52: -4730.1535 | AA52: -5001.8409 | AB52: -5289.0762 | AC52: -5592.746 | AD52: -5913.7873 | AE52: -6253.1903 | AF52: -6612.0016 | AG52: -6943.161
B53: -1775.46 | C53: -2471.989 | D53: -2339.9114 | E53: -2496.9928 | F53: -2176.6949 | G53: -2333.2804 | H53: -2193.5983 | I53: -2300.093 | J53: -2803.5863 | K53: -2698.4969 | L53: -2442.7208 | M53: -3020.4539 | N53: -2192.3099 | O53: -2208.9456 | P53: -2225.1367 | Q53: -2234.3175 | R53: -2235.5223 | S53: -2227.0147 | T53: -2215.4569 | U53: -2204.5613 | V53: -2192.6965 | W53: -2209.1143 | X53: -1883.0124 | Y53: -1987.0076 | Z53: -2094.052 | AA53: -2204.0009 | AB53: -2335.5156 | AC53: -2472.9785 | AD53: -2616.5891 | AE53: -2766.5444 | AF53: -2923.0372 | AG53: -3153.9046
B55: 2025 | C55: 2026F | D55: 2027F | E55: 2028F | F55: 2029F | G55: 2030F | H55: 2031F | I55: 2032F | J55: 2033F | K55: 2034F | L55: 2035F | M55: 2036F | N55: 2037F | O55: 2038F | P55: 2039F | Q55: 2040F | R55: 2041F | S55: 2042F | T55: 2043F | U55: 2044F | V55: 2045F | W55: 2046F | X55: 2047F | Y55: 2048F | Z55: 2049F | AA55: 2050F | AB55: 2051F | AC55: 2052F | AD55: 2053F | AE55: 2054F | AF55: 2055F
B56: 37637.553 | C56: 32305.278 | D56: 34215.353 | E56: 36305.327 | F56: 38310.94 | G56: 40487.215 | H56: 42732.128 | I56: 45115.971 | J56: 47833.677 | K56: 50583.873 | L56: 53297.186 | M56: 56354.423 | N56: 58875.41 | O56: 61991.459 | P56: 65273.264 | Q56: 69663.884 | R56: 73586.783 | S56: 77731.905 | T56: 82111.892 | U56: 86740.102 | V56: 91630.659 | W56: 96835.085 | X56: 102153.5 | Y56: 108002.36 | Z56: 114185.78 | AA56: 120722.91 | AB56: 127633.96 | AC56: 134940.34 | AD56: 142664.63 | AE56: 150830.76 | AF56: 159463.99
B57: 37637.553 | C57: 32713.989 | D57: 34456.911 | E57: 36510.993 | F57: 38259.695 | G57: 40412.28 | H57: 42436.598 | I57: 44783.093 | J57: 47666.586 | K57: 50273.497 | L57: 52766.721 | M57: 56057.454 | N57: 58069.52 | O57: 61090.919 | P57: 64273.23 | Q57: 68552.758 | R57: 72351.806 | S57: 76358.378 | T57: 80591.563 | U57: 85068.209 | V57: 89800.573 | W57: 94830.011 | X57: 99806.4 | Y57: 105516.19 | Z57: 111549.68 | AA57: 117925.07 | AB57: 124680.4 | AC57: 131820.57 | AD57: 139367.44 | AE57: 147344.12 | AF57: 155775.02

Sheet GDP
B1: 1996 | C1: 1997 | D1: 1998 | E1: 1999 | F1: 2000 | G1: 2001 | H1: 2002 | I1: 2003 | J1: 2004 | K1: 2005 | L1: 2006 | M1: 2007 | N1: 2008 | O1: 2009 | P1: 2010 | Q1: 2011 | R1: 2012 | S1: 2013 | T1: 2014 | U1: 2015 | V1: 2016 | W1: 2017 | X1: 2018 | Y1: 2019 | Z1: 2020 | AA1: 2021 | AB1: 2022 | AC1: 2023 | AD1: 2024 | AE1: 2025 | AF1: 2026 | AG1: 2027 | AH1: 2028 | AI1: 2029 | AJ1: 2030 | AK1: 2031 | AL1: 2032 | AM1: 2033 | AN1: 2034 | AO1: 2035 | AP1: 2036 | AQ1: 2037 | AR1: 2038 | AS1: 2039 | AT1: 2040 | AU1: 2041 | AV1: 2042 | AW1: 2043 | AX1: 2044 | AY1: 2045 | AZ1: 2046 | BA1: 2047 | BB1: 2048 | BC1: 2049 | BD1: 2050 | BE1: 2051 | BF1: 2052 | BG1: 2053 | BH1: 2054 | BI1: 2055 | BJ1: 2056
A2: Real GDP (trillions of 2017 dollars) | B2: 11.8436 | C2: 12.3703 | D2: 12.9249 | E2: 13.5438 | F2: 14.096 | G2: 14.2307 | H2: 14.4727 | I2: 14.8773 | J2: 15.4498 | K2: 15.988 | L2: 16.4332 | M2: 16.7625 | N2: 16.7815 | O2: 16.3491 | P2: 16.7898 | Q2: 17.0524 | R2: 17.4428 | S2: 17.8122 | T2: 18.2617 | U2: 18.7996 | V2: 19.1417 | W2: 19.6121 | X2: 20.1939 | Y2: 20.7157 | Z2: 20.2845 | AA2: 21.5324 | AB2: 22.0759 | AC2: 22.7237 | AD2: 23.3584 | AE2: 23.8303 | AF2: 24.3938 | AG2: 24.8477 | AH2: 25.2963 | AI2: 25.7402 | AJ2: 26.1994 | AK2: 26.6647 | AL2: 27.134 | AM2: 27.6137 | AN2: 28.1022 | AO2: 28.6004 | AP2: 29.1055 | AQ2: 29.6149 | AR2: 30.1317 | AS2: 30.6532 | AT2: 31.1886 | AU2: 31.7296 | AV2: 32.273 | AW2: 32.8231 | AX2: 33.3782 | AY2: 33.9277 | AZ2: 34.4741 | BA2: 35.0228 | BB2: 35.5741 | BC2: 36.1278 | BD2: 36.6814 | BE2: 37.2368 | BF2: 37.7955 | BG2: 38.3596 | BH2: 38.9296 | BI2: 39.507 | BJ2: 40.0935
A3: Nominal GDP (trillions of dollars, by calendar year) | B3: 8.0731 | C3: 8.5776 | D3: 9.0628 | E3: 9.6312 | F3: 10.251 | G3: 10.5819 | H3: 10.9291 | I3: 11.4565 | J3: 12.2172 | K3: 13.0392 | L3: 13.8156 | M3: 14.4743 | N3: 14.7699 | O3: 14.4781 | P3: 15.049 | Q3: 15.5997 | R3: 16.254 | S3: 16.8807 | T3: 17.6081 | U3: 18.295 | V3: 18.8049 | W3: 19.6121 | X3: 20.6565 | Y3: 21.54 | Z3: 21.3753 | AA3: 23.7257 | AB3: 26.0546 | AC3: 27.8115 | AD3: 29.298 | AE3: 30.7052 | AF3: 32.2742 | AG3: 33.6515 | AH3: 35.0019 | AI3: 36.3507 | AJ3: 37.7425 | AK3: 39.1748 | AL3: 40.6504 | AM3: 42.1854 | AN3: 43.7766 | AO3: 45.4309 | AP3: 47.1467 | AQ3: 48.9235 | AR3: 50.7696 | AS3: 52.6807 | AT3: 54.6739 | AU3: 56.7366 | AV3: 58.8639 | AW3: 61.0661 | AX3: 63.342 | AY3: 65.6728 | AZ3: 68.0645 | BA3: 70.5302 | BB3: 73.0732 | BC3: 75.695 | BD3: 78.3926 | BE3: 81.1722 | BF3: 84.04 | BG3: 87.0037 | BH3: 90.0672 | BI3: 93.2378 | BJ3: 96.5216
A4: Growth of the GDP price index | B4: 1.828 | C4: 1.733 | D4: 1.101 | E4: 1.401 | F4: 2.285 | G4: 2.305 | H4: 1.498 | I4: 2.002 | J4: 2.671 | K4: 3.121 | L4: 3.111 | M4: 2.708 | N4: 1.882 | O4: 0.658 | P4: 1.199 | Q4: 2.061 | R4: 1.869 | S4: 1.727 | T4: 1.741 | U4: 0.871 | V4: 0.957 | W4: 1.824 | X4: 2.29 | Y4: 1.653 | Z4: 1.362 | AA4: 4.54 | AB4: 7.125 | AC4: 3.688 | AD4: 2.485 | AE4: 2.726 | AF4: 2.676 | AG4: 2.363 | AH4: 2.168 | AI4: 2.062 | AJ4: 2.009 | AK4: 1.983 | AL4: 1.972 | AM4: 1.973 | AN4: 1.967 | AO4: 1.971 | AP4: 1.975 | AQ4: 1.983 | AR4: 1.993 | AS4: 1.998 | AT4: 2.001 | AU4: 2.003 | AV4: 2.002 | AW4: 2.002 | AX4: 2.002 | AY4: 2 | AZ4: 1.999 | BA4: 1.999 | BB4: 1.999 | BC4: 2 | BD4: 2 | BE4: 2.001 | BF4: 2.002 | BG4: 2.004 | BH4: 2.005 | BI4: 2.007 | BJ4: 2.007
A5: Real GDP (trillions of dollars) | B5: =B3/(1+B4/100) -> 7.928173 | C5: =C3/(1+C4/100) -> 8.4314824 | D5: =D3/(1+D4/100) -> 8.9641052 | E5: =E3/(1+E4/100) -> 9.4981312 | F5: =F3/(1+F4/100) -> 10.021997 | G5: =G3/(1+G4/100) -> 10.343483 | H5: =H3/(1+H4/100) -> 10.767798 | I5: =I3/(1+I4/100) -> 11.231643 | ... AA5: =AA3/(1+AA4/100) -> 22.695332 | AB5: 26.770514 | AC5: 28.424722 | AD5: 29.825182 | AE5: 31.49007 | AF5: =AF3/(1+AF4/100) -> 31.433052 | AG5: =AG3/(1+AG4/100) -> 32.874672 | AH5: =AH3/(1+AH4/100) -> 34.259161 | AI5: =AI3/(1+AI4/100) -> 35.616292 | AJ5: =AJ3/(1+AJ4/100) -> 36.999186 | AK5: =AK3/(1+AK4/100) -> 38.413069 | AL5: =AL3/(1+AL4/100) -> 39.864276 | AM5: =AM3/(1+AM4/100) -> 41.369186 | ... BJ5: =BJ3/(1+BJ4/100) -> 94.622526
A6: Growth% real | C6: =(C5-B5)/B5 -> 0.063483657 | D6: =(D5-C5)/C5 -> 0.063170717 | E6: =(E5-D5)/D5 -> 0.059573819 | F6: =(F5-E5)/E5 -> 0.055154658 | G6: =(G5-F5)/F5 -> 0.032077973 | H6: =(H5-G5)/G5 -> 0.041022513 | I6: =(I5-H5)/H5 -> 0.043076971 | J6: =(J5-I5)/I5 -> 0.059450376 | ... BJ6: =(BJ5-BI5)/BI5 -> 0.035219621
A7: Growth% nominal | C7: =(C3-B3)/B3 -> 0.062491484 | D7: =(D3-C3)/C3 -> 0.056565939 | E7: =(E3-D3)/D3 -> 0.062717924 | F7: =(F3-E3)/E3 -> 0.064353352 | G7: =(G3-F3)/F3 -> 0.032279778 | H7: =(H3-G3)/G3 -> 0.032810743 | I7: =(I3-H3)/H3 -> 0.04825649 | J7: =(J3-I3)/I3 -> 0.066398987 | ... BJ7: =(BJ3-BI3)/BI3 -> 0.035219621
A9: Spending multiplier | B9: IncomeTax multiplier | D9: Corp Tax | E9: Payroll Tax | F9: infra | G9: others
A10: 2 | B10: 1.5 | D10: 0.4 | E10: 1.3 | F10: 1.2 | G10: 1
A11: 1 | B11: 0.75 | D11: 0.2 | E11: 0.8 | F11: 0.85 | G11: 0.8
A12: 0.5 | B12: 0.1 | D12: 0 | E12: 0.3 | F12: 0.5 | G12: 0.6
B14: 2026 | C14: 2027 | D14: 2028 | E14: 2029 | F14: 2030 | G14: 2031 | H14: 2032 | I14: 2033 | J14: 2034 | K14: 2035 | L14: 2036 | M14: 2037 | N14: 2038 | O14: 2039 | P14: 2040 | Q14: 2041 | R14: 2042 | S14: 2043 | T14: 2044 | U14: 2045 | V14: 2046 | W14: 2047 | X14: 2048 | Y14: 2049 | Z14: 2050 | AA14: 2051 | AB14: 2052 | AC14: 2053 | AD14: 2054 | AE14: 2055 | AF14: 2056
B15: bad | C15: bad | D15: bad | E15: normal | F15: normal | G15: normal | H15: good | I15: good | J15: good | K15: normal | L15: normal | M15: normal | N15: normal | O15: bad | P15: bad | Q15: bad | R15: normal | S15: normal | T15: normal | U15: good | V15: good | W15: good | X15: normal | Y15: normal | Z15: normal | AA15: normal | AB15: bad | AC15: bad | AD15: bad | AE15: normal | AF15: normal
A16: Spending multiplier | B16: {=_xlfn.IFS(B$15="bad", $A$10, B$15="normal", $A$11, B$15="good", $A$12)} -> 2 | C16: {=_xlfn.IFS(C$15="bad", $A$10, C$15="normal", $A$11, C$15="good", $A$12)} -> 2 | D16: {=_xlfn.IFS(D$15="bad", $A$10, D$15="normal", $A$11, D$15="good", $A$12)} -> 2 | E16: {=_xlfn.IFS(E$15="bad", $A$10, E$15="normal", $A$11, E$15="good", $A$12)} -> 1 | F16: {=_xlfn.IFS(F$15="bad", $A$10, F$15="normal", $A$11, F$15="good", $A$12)} -> 1 | G16: {=_xlfn.IFS(G$15="bad", $A$10, G$15="normal", $A$11, G$15="good", $A$12)} -> 1 | H16: {=_xlfn.IFS(H$15="bad", $A$10, H$15="normal", $A$11, H$15="good", $A$12)} -> 0.5 | I16: {=_xlfn.IFS(I$15="bad", $A$10, I$15="normal", $A$11, I$15="good", $A$12)} -> 0.5 | ... AF16: {=_xlfn.IFS(AF$15="bad", $A$10, AF$15="normal", $A$11, AF$15="good", $A$12)} -> 1
A17: IncomeTax multiplier | B17: {=_xlfn.IFS(B$15="bad", $B$10, B$15="normal", $B$11, B$15="good", $B$12)} -> 1.5 | C17: {=_xlfn.IFS(C$15="bad", $B$10, C$15="normal", $B$11, C$15="good", $B$12)} -> 1.5 | D17: {=_xlfn.IFS(D$15="bad", $B$10, D$15="normal", $B$11, D$15="good", $B$12)} -> 1.5 | E17: {=_xlfn.IFS(E$15="bad", $B$10, E$15="normal", $B$11, E$15="good", $B$12)} -> 0.75 | F17: {=_xlfn.IFS(F$15="bad", $B$10, F$15="normal", $B$11, F$15="good", $B$12)} -> 0.75 | G17: {=_xlfn.IFS(G$15="bad", $B$10, G$15="normal", $B$11, G$15="good", $B$12)} -> 0.75 | H17: {=_xlfn.IFS(H$15="bad", $B$10, H$15="normal", $B$11, H$15="good", $B$12)} -> 0.1 | I17: {=_xlfn.IFS(I$15="bad", $B$10, I$15="normal", $B$11, I$15="good", $B$12)} -> 0.1 | ... AF17: {=_xlfn.IFS(AF$15="bad", $B$10, AF$15="normal", $B$11, AF$15="good", $B$12)} -> 0.75
A18: Corp Tax | B18: {=_xlfn.IFS(B$15="bad", $D$10, B$15="normal", $D$11, B$15="good", $D$12)} -> 0.4 | C18: {=_xlfn.IFS(C$15="bad", $D$10, C$15="normal", $D$11, C$15="good", $D$12)} -> 0.4 | D18: {=_xlfn.IFS(D$15="bad", $D$10, D$15="normal", $D$11, D$15="good", $D$12)} -> 0.4 | E18: {=_xlfn.IFS(E$15="bad", $D$10, E$15="normal", $D$11, E$15="good", $D$12)} -> 0.2 | F18: {=_xlfn.IFS(F$15="bad", $D$10, F$15="normal", $D$11, F$15="good", $D$12)} -> 0.2 | G18: {=_xlfn.IFS(G$15="bad", $D$10, G$15="normal", $D$11, G$15="good", $D$12)} -> 0.2 | H18: {=_xlfn.IFS(H$15="bad", $D$10, H$15="normal", $D$11, H$15="good", $D$12)} -> 0 | I18: {=_xlfn.IFS(I$15="bad", $D$10, I$15="normal", $D$11, I$15="good", $D$12)} -> 0 | ... AF18: {=_xlfn.IFS(AF$15="bad", $D$10, AF$15="normal", $D$11, AF$15="good", $D$12)} -> 0.2
A19: Payroll Tax | B19: {=_xlfn.IFS(B$15="bad", $E$10, B$15="normal", $E$11, B$15="good", $E$12)} -> 1.3 | C19: {=_xlfn.IFS(C$15="bad", $E$10, C$15="normal", $E$11, C$15="good", $E$12)} -> 1.3 | D19: {=_xlfn.IFS(D$15="bad", $E$10, D$15="normal", $E$11, D$15="good", $E$12)} -> 1.3 | E19: {=_xlfn.IFS(E$15="bad", $E$10, E$15="normal", $E$11, E$15="good", $E$12)} -> 0.8 | F19: {=_xlfn.IFS(F$15="bad", $E$10, F$15="normal", $E$11, F$15="good", $E$12)} -> 0.8 | G19: {=_xlfn.IFS(G$15="bad", $E$10, G$15="normal", $E$11, G$15="good", $E$12)} -> 0.8 | H19: {=_xlfn.IFS(H$15="bad", $E$10, H$15="normal", $E$11, H$15="good", $E$12)} -> 0.3 | I19: {=_xlfn.IFS(I$15="bad", $E$10, I$15="normal", $E$11, I$15="good", $E$12)} -> 0.3 | ... AF19: {=_xlfn.IFS(AF$15="bad", $E$10, AF$15="normal", $E$11, AF$15="good", $E$12)} -> 0.8
A20: Infrastructure spending | B20: {=_xlfn.IFS(B$15="bad", $F$10, B$15="normal", $F$11, B$15="good", $F$12)} -> 1.2 | C20: {=_xlfn.IFS(C$15="bad", $F$10, C$15="normal", $F$11, C$15="good", $F$12)} -> 1.2 | D20: {=_xlfn.IFS(D$15="bad", $F$10, D$15="normal", $F$11, D$15="good", $F$12)} -> 1.2 | E20: {=_xlfn.IFS(E$15="bad", $F$10, E$15="normal", $F$11, E$15="good", $F$12)} -> 0.85 | F20: {=_xlfn.IFS(F$15="bad", $F$10, F$15="normal", $F$11, F$15="good", $F$12)} -> 0.85 | G20: {=_xlfn.IFS(G$15="bad", $F$10, G$15="normal", $F$11, G$15="good", $F$12)} -> 0.85 | H20: {=_xlfn.IFS(H$15="bad", $F$10, H$15="normal", $F$11, H$15="good", $F$12)} -> 0.5 | I20: {=_xlfn.IFS(I$15="bad", $F$10, I$15="normal", $F$11, I$15="good", $F$12)} -> 0.5 | ... AF20: {=_xlfn.IFS(AF$15="bad", $F$10, AF$15="normal", $F$11, AF$15="good", $F$12)} -> 0.85
A21: Others Taxes | B21: {=_xlfn.IFS(B$15="bad", $G$10, B$15="normal", $G$11, B$15="good", $G$12)} -> 1 | C21: {=_xlfn.IFS(C$15="bad", $G$10, C$15="normal", $G$11, C$15="good", $G$12)} -> 1 | D21: {=_xlfn.IFS(D$15="bad", $G$10, D$15="normal", $G$11, D$15="good", $G$12)} -> 1 | E21: {=_xlfn.IFS(E$15="bad", $G$10, E$15="normal", $G$11, E$15="good", $G$12)} -> 0.8 | F21: {=_xlfn.IFS(F$15="bad", $G$10, F$15="normal", $G$11, F$15="good", $G$12)} -> 0.8 | G21: {=_xlfn.IFS(G$15="bad", $G$10, G$15="normal", $G$11, G$15="good", $G$12)} -> 0.8 | H21: {=_xlfn.IFS(H$15="bad", $G$10, H$15="normal", $G$11, H$15="good", $G$12)} -> 0.6 | I21: {=_xlfn.IFS(I$15="bad", $G$10, I$15="normal", $G$11, I$15="good", $G$12)} -> 0.6 | ... AF21: {=_xlfn.IFS(AF$15="bad", $G$10, AF$15="normal", $G$11, AF$15="good", $G$12)} -> 0.8
A24: https://www.crfb.org/papers/comparing-fiscal-multipliers
A25: https://www.cbo.gov/sites/default/files/114th-congress-2015-2016/workingpaper/49925-FiscalMultiplier_1.pdf
A26: https://www.richmondfed.org/publications/research/econ_focus/2018/q4/jargon_alert
A27: Year | B27: 2022 | C27: 2023 | D27: 2024 | E27: 2025 | F27: 2026 | G27: 2027 | H27: 2028 | I27: 2029 | J27: 2030 | K27: 2031 | L27: 2032 | M27: 2033 | N27: 2034 | O27: 2035 | P27: 2036
A28: GDP | B28: 25565.375 | C28: 27397.95 | D28: 28947.9 | E28: 30330.329 | F28: 31902.006 | G28: 33315.187 | H28: 34665.785 | I28: 36010.049 | J28: 37390.673 | K28: 38812.821 | L28: 40276.526 | M28: 41795.93 | N28: 43373.323 | O28: 45011.5 | P28: 46712.142
A31: Table 2-1. CBO’s Economic Projections for Calendar Years 2026 to 2036
A32: Percent
F33: Annual average
B34: Estimated, 2025 | C34: 2026 | D34: 2027 | E34: 2028 | F34: 2029– 2030 | G34: 2031– 2036
B35: Change from fourth quarter to fourth quarter
A36: Gross domestic product
A37: Real | B37: 1.9 | C37: 2.2 | D37: 1.8 | E37: 1.8 | F37: 1.8 | G37: 1.8
A38: Nominal | B38: 5 | C38: 4.8 | D38: 4.1 | E38: 3.9 | F38: 3.8 | G38: 3.8
A39: Inflation
A40: PCE price index | B40: 2.8 | C40: 2.7 | D40: 2.3 | E40: 2.1 | F40: 2 | G40: 2
A41: Core PCE price index | B41: 2.9 | C41: 2.8 | D41: 2.3 | E41: 2.2 | F41: 2 | G41: 2
A42: Consumer price index | B42: 3 | C42: 2.8 | D42: 2.4 | E42: 2.3 | F42: 2.3 | G42: 2.3
A43: Core consumer price index | B43: 3.1 | C43: 3 | D43: 2.4 | E43: 2.3 | F43: 2.3 | G43: 2.3
A44: GDP price index | B44: 3 | C44: 2.5 | D44: 2.3 | E44: 2.1 | F44: 2 | G44: 2
A45: Employment cost index | B45: 3.4 | C45: 3.5 | D45: 3.2 | E45: 3.1 | F45: 3 | G45: 2.9
A46: Payroll employment (average monthly change, in thousands) | B46: 70 | C46: 105 | D46: 31 | E46: 42 | F46: 43 | G46: 45
B47: Fourth-quarter level
A48: Unemployment rate | B48: 4.5 | C48: 4.6 | D48: 4.5 | E48: 4.4 | F48: 4.3 | G48: 4.2
B49: Change from year to year
A50: Gross Domestic Product
A51: Real | B51: 2 | C51: 2.4 | D51: 1.9 | E51: 1.8 | F51: 1.8 | G51: 1.8
A52: Nominal | B52: 4.8 | C52: 5.1 | D52: 4.3 | E52: 4 | F52: 3.8 | G52: 3.8
A53: Inflation
A54: PCE price index | B54: 2.6 | C54: 2.7 | D54: 2.4 | E54: 2.2 | F54: 2.1 | G54: 2
A55: Core PCE price index | B55: 2.8 | C55: 2.9 | D55: 2.4 | E55: 2.2 | F55: 2.1 | G55: 2
A56: Consumer price index | B56: 2.8 | C56: 2.9 | D56: 2.5 | E56: 2.4 | F56: 2.3 | G56: 2.3
A57: Core consumer price index | B57: 3 | C57: 3.1 | D57: 2.6 | E57: 2.4 | F57: 2.3 | G57: 2.3
A58: GDP price index | B58: 2.7 | C58: 2.7 | D58: 2.4 | E58: 2.2 | F58: 2 | G58: 2
A59: Employment cost index | B59: 3.5 | C59: 3.4 | D59: 3.4 | E59: 3.1 | F59: 3 | G59: 2.9
B60: Annual average
A61: Unemployment rate | B61: 4.3 | C61: 4.6 | D61: 4.5 | E61: 4.5 | F61: 4.3 | G61: 4.2
A62: Interest rates
A63: Effective federal funds rate | B63: 4.2 | C63: 3.5 | D63: 3.4 | E63: 3.4 | F63: 3.4 | G63: 3.4
A64: 3-month Treasury bills | B64: 4.1 | C64: 3.3 | D64: 3.2 | E64: 3.2 | F64: 3.2 | G64: 3.1
A65: 10-year Treasury notes | B65: 4.3 | C65: 4.1 | D65: 4.3 | E65: 4.3 | F65: 4.3 | G65: 4.4
A66: Tax bases (percentage of GDP)
A67: Wages and salaries | B67: 42.3 | C67: 42 | D67: 42 | E67: 42.1 | F67: 42.1 | G67: 42.1
A68: Domestic corporate profits | B68: 11.3 | C68: 11.1 | D68: 10.8 | E68: 10.4 | F68: 10 | G68: 10

Sheet Tariff
A1: Tariff Tracker: 2026 Trump Tariffs & Trade War by the Numbers
A2: Calendar Year | B2: 2025 | C2: 2026 | D2: 2027 | E2: 2028 | F2: 2029 | G2: 2030 | H2: 2031 | I2: 2032 | J2: 2033 | K2: 2034 | L2: 2035 | M2: 2026-2035
A3: Section 232 Tariffs | B3: 23.2 | C3: 42.8 | D3: 43.6 | E3: 45.3 | F3: 46 | G3: 47.7 | H3: 49.5 | I3: 50.9 | J3: 53.1 | K3: 54.9 | L3: 55.9 | M3: 489.6
A4: Section 232 Steel and Aluminum | B4: 6.2 | C4: 7.3 | D4: 7.4 | E4: 7.9 | F4: 8.1 | G4: 8.4 | H4: 8.8 | I4: 8.9 | J4: 9.5 | K4: 9.7 | L4: 9.8 | M4: 85.7
A5: Section 232 Autos and Auto Parts | B5: 17.1 | C5: 28.2 | D5: 28.5 | E5: 29.2 | F5: 29.7 | G5: 30.7 | H5: 31.8 | I5: 32.8 | J5: 34 | K5: 35.1 | L5: 35.9 | M5: 315.9
A6: Section 232 Copper | B6: 0.3 | C6: 0.7 | D6: 0.7 | E6: 0.8 | F6: 0.8 | G6: 0.8 | H6: 0.9 | I6: 0.9 | J6: 0.9 | K6: 1 | L6: 1 | M6: 8.5
A7: Section 232 Furniture, Kithcen Cabinets and Vanities, Lumber | B7: 0.2 | C7: 1.1 | D7: 1.3 | E7: 1.3 | F7: 1.4 | G7: 1.4 | H7: 1.5 | I7: 1.5 | J7: 1.6 | K7: 1.7 | L7: 1.7 | M7: 14.4 | O7: tariff content, trend
A8: Section 232 Heavy Trucks and Parts | B8: -0.6 | C8: 5.5 | D8: 5.7 | E8: 6 | F8: 6.1 | G8: 6.4 | H8: 6.6 | I8: 6.8 | J8: 7.1 | K8: 7.4 | L8: 7.5 | M8: 65 | O8: other taxes
O9: corp tax
A10: Section 122 Tariff (10%) | B10: 0 | C10: 25.3 | D10: 0 | E10: 0 | F10: 0 | G10: 0 | H10: 0 | I10: 0 | J10: 0 | K10: 0 | L10: 0 | M10: 25.3 | O10: create financial chart
A11: Section 122 Tariff (15%) | B11: 0 | C11: 33.2 | D11: 0 | E11: 0 | F11: 0 | G11: 0 | H11: 0 | I11: 0 | J11: 0 | K11: 0 | L11: 0 | M11: 33.2 | O11: gdp changes
A13: Total | B13: 23.2 | C13: 76 | D13: 43.6 | E13: 45.3 | F13: 46 | G13: 47.7 | H13: 49.5 | I13: 50.9 | J13: 53.1 | K13: 54.9 | L13: 55.9 | M13: 522.8
A15: IEEPA Tariffs | B15: 72 | C15: 93.9 | D15: 95.7 | E15: 99.7 | F15: 101.9 | G15: 106.1 | H15: 110.3 | I15: 113.7 | J15: 118.7 | K15: 122.4 | L15: 125.1 | M15: 1087.5
A16: IEEPA Fentanyl China | B16: 23.1 | C16: 19 | D16: 19.6 | E16: 20.5 | F16: 20.9 | G16: 22 | H16: 22.7 | I16: 23.4 | J16: 24.5 | K16: 25.4 | L16: 25.9 | M16: 224
A17: IEEPA Mexico | B17: 1.9 | C17: 2.8 | D17: 2.9 | E17: 3 | F17: 3 | G17: 3.1 | H17: 3.2 | I17: 3.2 | J17: 3.3 | K17: 3.5 | L17: 3.5 | M17: 31.6
A18: IEEPA Canada | B18: 1.9 | C18: 3.1 | D18: 3.1 | E18: 3.2 | F18: 3.2 | G18: 3.3 | H18: 3.4 | I18: 3.5 | J18: 3.6 | K18: 3.7 | L18: 3.8 | M18: 33.8
A19: IEEPA 10% Baseline Tariff Excluding Canada and Mexico | B19: 35.4 | C19: 47.9 | D19: 49.2 | E19: 51.1 | F19: 52.5 | G19: 54.7 | H19: 56.9 | I19: 59.1 | J19: 61.6 | K19: 63.7 | L19: 65.5 | M19: 562.3
A20: IEEPA "Reciprocal" Tariff Increases (ROW) | B20: 6.4 | C20: 16.6 | D20: 16.6 | E20: 17.2 | F20: 17.6 | G20: 18.2 | H20: 19 | I20: 19.5 | J20: 20.4 | K20: 21 | L20: 21.5 | M20: 187.7
A21: Ending De Minimis | B21: 3.2 | C21: 4.5 | D21: 4.4 | E21: 4.6 | F21: 4.6 | G21: 4.8 | H21: 5 | I21: 5 | J21: 5.3 | K21: 5.1 | L21: 4.8 | M21: 48.2
A23: Retaliation | B23: -8.6 | C23: -9.6 | D23: -10.8 | E23: -11.6 | F23: -12.5 | G23: -13.2 | H23: -14 | I23: -14.9 | J23: -15.6 | K23: -16.4 | L23: -17.4 | M23: -136

Sheet Gov Debt
A1: observation_date | B1: GFDEBTN | D1: Year | E1: 2022 | F1: 2023 | G1: 2024 | H1: 2025
A2: 44562 | B2: 30400960 | E2: =B5 -> 31419689 | F2: =B9 -> 34001494 | G2: =B13 -> 36218605 | H2: 37637553
A3: 44652 | B3: 30568582
A4: 44743 | B4: 30928912
A5: 44835 | B5: 31419689
A6: 44927 | B6: 31458438
A7: 45017 | B7: 32332274
A8: 45108 | B8: 33167334
A9: 45200 | B9: 34001494
A10: 45292 | B10: 34586533
A11: 45383 | B11: 34831634
A12: 45474 | B12: 35464674
A13: 45566 | B13: 36218605
A14: 45658 | B14: 36214310
... A16: 45839 | B16: 37637553
A17: 45931
A18: 46023 | B18: 38514009
A21: Table 1-3. CBO's Baseline Projections of Federal Debt
A22: Billions of dollars
B24: Actual, 2025 | C24: 2026 | D24: 2027 | E24: 2028 | F24: 2029 | G24: 2030 | H24: 2031 | I24: 2032 | J24: 2033 | K24: 2034 | L24: 2035 | M24: 2036 | N24: 2037 | O24: 2038 | P24: 2039 | Q24: 2040 | R24: 2041 | S24: 2042 | T24: 2043 | U24: 2044 | V24: 2045 | W24: 2046 | X24: 2047 | Y24: 2048 | Z24: 2049 | AA24: 2050 | AB24: 2051 | AC24: 2052 | AD24: 2053 | AE24: 2054 | AF24: 2055
A25: Debt held by the public at the beginning of the year | B25: 28196 | C25: 30172 | D25: 32095 | E25: 34005 | F25: 36093 | G25: 38103 | H25: 40280 | I25: 42528 | J25: 44922 | K25: 47644 | L25: 50394 | M25: 53103
A27: Changes in debt held by the public
A28: Resulting from the deficit | B28: 1775 | C28: 1853 | D28: 1887 | E28: 2080 | F28: 2020 | G28: 2201 | H28: 2286 | I28: 2439 | J28: 2781 | K28: 2819 | L28: 2779 | M28: 3115
A29: Resulting from other means of financing | B29: 201 | C29: 70 | D29: 22 | E29: 9 | F29: -10 | G29: -24 | H29: -37 | I29: -45 | J29: -59 | K29: -69 | L29: -70 | M29: -66
A30: growth% | C30: =(C29-B29)/B29 -> -0.65174129 | D30: =(D29-C29)/C29 -> -0.68571429 | E30: =(E29-D29)/D29 -> -0.59090909 | F30: =(F29-E29)/E29 -> -2.1111111 | G30: =(G29-F29)/F29 -> 1.4 | H30: =(H29-G29)/G29 -> 0.54166667 | I30: =(I29-H29)/H29 -> 0.21621622 | J30: =(J29-I29)/I29 -> 0.31111111 | ... M30: =(M29-L29)/L29 -> -0.057142857
A31: Total | B31: 1977 | C31: 1923 | D31: 1909 | E31: 2088 | F31: 2010 | G31: 2177 | H31: 2249 | I31: 2394 | J31: 2722 | K31: 2750 | L31: 2709 | M31: 3049
A33: Debt held by the public at the end of the year
A34: In billions of dollars | B34: 30172 | C34: 32095 | D34: 34005 | E34: 36093 | F34: 38103 | G34: 40280 | H34: 42528 | I34: 44922 | J34: 47644 | K34: 50394 | L34: 53103 | M34: 56152
A35: As a percentage of GDP | B35: 99.4 | C35: 100.6 | D35: 102.1 | E35: 104.1 | F35: 105.8 | G35: 107.7 | H35: 109.6 | I35: 111.5 | J35: 114 | K35: 116.2 | L35: 118 | M35: 120.2
A37: Addendum:
A38: Federal financial assets | B38: 2259 | C38: 2329 | D38: 2351 | E38: 2360 | F38: 2350 | G38: 2327 | H38: 2290 | I38: 2244 | J38: 2185 | K38: 2116 | L38: 2047 | M38: 1981
A39: growth% | C39: =(C38-B38)/B38 -> 0.030987162 | D39: =(D38-C38)/C38 -> 0.0094461142 | E39: =(E38-D38)/D38 -> 0.0038281582 | F39: =(F38-E38)/E38 -> -0.0042372881 | G39: =(G38-F38)/F38 -> -0.009787234 | H39: =(H38-G38)/G38 -> -0.015900301 | I39: =(I38-H38)/H38 -> -0.020087336 | J39: =(J38-I38)/I38 -> -0.026292335 | ... M39: =(M38-L38)/L38 -> -0.032242306
A40: Debt minus financial assets
A41: In billions of dollars | B41: 27913 | C41: 29766 | D41: 31653 | E41: 33733 | F41: 35752 | G41: 37953 | H41: 40239 | I41: 42678 | J41: 45459 | K41: 48277 | L41: 51056 | M41: 54172
A42: As a percentage of GDP | B42: 91.9 | C42: 93.3 | D42: 95 | E42: 97.3 | F42: 99.3 | G42: 101.5 | H42: 103.7 | I42: 106 | J42: 108.8 | K42: 111.3 | L42: 113.4 | M42: 116
A44: Federal Reserve's holdings of debt held by the public | B44: 4201 | C44: 4540 | D44: 4973 | E44: 5484 | F44: 6048 | G44: 6595 | H44: 7067 | I44: 7537 | J44: 8004 | K44: 8496 | L44: 8981 | M44: 9466
A45: growth% | C45: =(C44-B44)/B44 -> 0.080695073 | D45: =(D44-C44)/C44 -> 0.095374449 | E45: =(E44-D44)/D44 -> 0.10275488 | F45: =(F44-E44)/E44 -> 0.10284464 | G45: =(G44-F44)/F44 -> 0.090443122 | H45: =(H44-G44)/G44 -> 0.071569371 | I45: =(I44-H44)/H44 -> 0.066506297 | J45: =(J44-I44)/I44 -> 0.061960992 | ... M45: =(M44-L44)/L44 -> 0.054002895
A46: Debt minus financial assets and Federal Reserve's holdings
A47: In billions of dollars | B47: 23712 | C47: 25226 | D47: 26680 | E47: 28249 | F47: 29704 | G47: 31358 | H47: 33172 | I47: 35141 | J47: 37455 | K47: 39782 | L47: 42075 | M47: 44706
A48: As a percentage of GDP | B48: 78.1 | C48: 79.1 | D48: 80.1 | E48: 81.5 | F48: 82.5 | G48: 83.9 | H48: 85.5 | I48: 87.2 | J48: 89.6 | K48: 91.7 | L48: 93.5 | M48: 95.7
A50: Gross federal debt | B50: 37373 | C50: 39430 | D50: 41279 | E50: 43297 | F50: 45192 | G50: 47192 | H50: 49218 | I50: 51480 | J50: 54379 | K50: 57359 | L50: 60386 | M50: 63693
A51: intragovernmental | B51: =B50-B34 -> 7201 | C51: =C50-C34 -> 7335 | D51: =D50-D34 -> 7274 | E51: =E50-E34 -> 7204 | F51: =F50-F34 -> 7089 | G51: =G50-G34 -> 6912 | H51: =H50-H34 -> 6690 | I51: =I50-I34 -> 6558 | ... M51: =M50-M34 -> 7541
A53: Debt subject to limit | B53: 37526 | C53: 39581 | D53: 41428 | E53: 43446 | F53: 45341 | G53: 47341 | H53: 49368 | I53: 51630 | J53: 54530 | K53: 57510 | L53: 60538 | M53: 63846
A55: Average interest rate on debt held by the public (percent) | B55: 3.4 | C55: 3.4 | D55: 3.4 | E55: 3.5 | F55: 3.6 | G55: 3.7 | H55: 3.8 | I55: 3.9 | J55: 3.9 | K55: 3.9 | L55: 3.9 | M55: 3.9
A58: debt held by public | B58: =B25 -> 28196 | C58: =C25 -> 30172 | D58: =D25 -> 32095 | E58: =E25 -> 34005 | F58: =F25 -> 36093 | G58: =G25 -> 38103 | H58: =H25 -> 40280 | I58: =I25 -> 42528 | ... M58: =M25 -> 53103
A59: growth% | C59: =(C58-B58)/B58 -> 0.070080863 | D59: =(D58-C58)/C58 -> 0.063734588 | E59: =(E58-D58)/D58 -> 0.059510827 | F59: =(F58-E58)/E58 -> 0.061402735 | G59: =(G58-F58)/F58 -> 0.055689469 | H59: =(H58-G58)/G58 -> 0.057134609 | I59: =(I58-H58)/H58 -> 0.055809335 | J59: =(J58-I58)/I58 -> 0.056292325 | ... M59: =(M58-L58)/L58 -> 0.0537564
A60: other financing | B60: =B29 -> 201 | C60: =C29 -> 70 | D60: =D29 -> 22 | E60: =E29 -> 9 | F60: =F29 -> -10 | G60: =G29 -> -24 | H60: =H29 -> -37 | I60: =I29 -> -45 | ... M60: =M29 -> -66 | N60: =$A$65/19 -> 77.421053 | O60: =$A$65/19 -> 77.421053 | P60: =$A$65/19 -> 77.421053 | Q60: =$A$65/19 -> 77.421053 | R60: =$A$65/19 -> 77.421053 | S60: =$A$65/19 -> 77.421053 | T60: =$A$65/19 -> 77.421053 | U60: =$A$65/19 -> 77.421053 | V60: =$A$65/19 -> 77.421053 | W60: 80 | X60: 80 | Y60: 80 | Z60: 80 | AA60: 80 | AB60: 80 | AC60: 80 | AD60: 80 | AE60: 80 | AF60: 80
A61: growth% | C61: =(C60-B60)/B60 -> -0.65174129 | D61: =(D60-C60)/C60 -> -0.68571429 | E61: =(E60-D60)/D60 -> -0.59090909 | F61: =(F60-E60)/E60 -> -2.1111111 | G61: =(G60-F60)/F60 -> 1.4 | H61: =(H60-G60)/G60 -> 0.54166667 | I61: =(I60-H60)/H60 -> 0.21621622 | J61: =(J60-I60)/I60 -> 0.31111111 | ... M61: =(M60-L60)/L60 -> -0.057142857
A62: intragovernmental | B62: =B51 -> 7201 | C62: =C51 -> 7335 | D62: =D51 -> 7274 | E62: =E51 -> 7204 | F62: =F51 -> 7089 | G62: =G51 -> 6912 | H62: =H51 -> 6690 | I62: =I51 -> 6558 | ... M62: =M51 -> 7541
A63: growth% | C63: =(C62-B62)/B62 -> 0.018608527 | D63: =(D62-C62)/C62 -> -0.0083162918 | E63: =(E62-D62)/D62 -> -0.0096233159 | F63: =(F62-E62)/E62 -> -0.015963354 | G63: =(G62-F62)/F62 -> -0.024968261 | H63: =(H62-G62)/G62 -> -0.032118056 | I63: =(I62-H62)/H62 -> -0.019730942 | J63: =(J62-I62)/I62 -> 0.026989936 | ... M63: =(M62-L62)/L62 -> 0.035424962
A65: =1750+SUM(C60:M60) -> 1471

Sheet Gov outlays
A1: This file presents data that supplement CBO’s February 2026 report The Budget and Economic Outlook: 2026 to 2036.
A2: www.cbo.gov/publication/61882
A5: Table 3-1. CBO's Baseline Projections of Outlays
N7: Total
B8: Actual, 2025 | C8: 2026 | D8: 2027 | E8: 2028 | F8: 2029 | G8: 2030 | H8: 2031 | I8: 2032 | J8: 2033 | K8: 2034 | L8: 2035 | M8: 2036 | N8: 2027– 2031 | O8: 2027– 2036
B9: In billions of dollars
A10: Mandatory
A11: Social Security | B11: 1575 | C11: 1666 | D11: 1769 | E11: 1875 | F11: 1979 | G11: 2083 | H11: 2190 | I11: 2298 | J11: 2409 | K11: 2519 | L11: 2632 | M11: 2747 | N11: 9895 | O11: 22500
A12: Medicare | B12: 1180 | C12: 1287 | D12: 1374 | E12: 1533 | F12: 1470 | G12: 1649 | H12: 1753 | I12: 1867 | J12: 2123 | K12: 2153 | L12: 2155 | M12: 2421 | N12: 7778 | O12: 18497
A13: Medicaid | B13: 668 | C13: 708 | D13: 726 | E13: 746 | F13: 754 | G13: 777 | H13: 804 | I13: 834 | J13: 870 | K13: 905 | L13: 941 | M13: 981 | N13: 3806 | O13: 8338
A14: Other spending | B14: 1114 | C14: 1281 | D14: 1327 | E14: 1284 | F14: 1326 | G14: 1371 | H14: 1377 | I14: 1400 | J14: 1466 | K14: 1472 | L14: 1458 | M14: 1555 | N14: 6685 | O14: 14036
A15: Offsetting receipts | B15: -370 | C15: -412 | D15: -413 | E15: -434 | F15: -462 | G15: -504 | H15: -541 | I15: -564 | J15: -591 | K15: -613 | L15: -642 | M15: -675 | N15: -2353 | O15: -5438
A16: Subtotal | B16: 4168 | C16: 4529 | D16: 4783 | E16: 5005 | F16: 5067 | G16: 5375 | H16: 5582 | I16: 5835 | J16: 6277 | K16: 6437 | L16: 6545 | M16: 7028 | N16: 25812 | O16: 57933
A18: Discretionary
A19: Defense | B19: 893 | C19: 885 | D19: 901 | E19: 928 | F19: 938 | G19: 966 | H19: 986 | I19: 1006 | J19: 1034 | K19: 1051 | L19: 1068 | M19: 1100 | N19: 4719 | O19: 9979
A20: Nondefense | B20: 980 | C20: 996 | D20: 981 | E20: 1001 | F20: 1010 | G20: 1023 | H20: 1039 | I20: 1057 | J20: 1076 | K20: 1096 | L20: 1119 | M20: 1144 | N20: 5053 | O20: 10545
A21: Subtotal | B21: 1872 | C21: 1880 | D21: 1882 | E21: 1929 | F21: 1948 | G21: 1989 | H21: 2024 | I21: 2063 | J21: 2111 | K21: 2147 | L21: 2187 | M21: 2244 | N21: 9772 | O21: 20524
A22: Net interest | B22: 970 | C22: 1039 | D22: 1108 | E22: 1218 | F22: 1324 | G22: 1432 | H22: 1548 | I22: 1670 | J22: 1784 | K22: 1904 | L22: 2019 | M22: 2144 | N22: 6630 | O22: 16152
A24: Total | B24: 7010 | C24: 7449 | D24: 7772 | E24: 8151 | F24: 8340 | G24: 8796 | H24: 9155 | I24: 9569 | J24: 10172 | K24: 10487 | L24: 10751 | M24: 11416 | N24: 42214 | O24: 94610
A25: On-budget | B25: 5578 | C25: 5928 | D25: 6151 | E25: 6426 | F25: 6513 | G25: 6864 | H25: 7113 | I25: 7409 | J25: 7911 | K25: 8125 | L25: 8286 | M25: 8847 | N25: 33066 | O25: 73644
A26: Off-budget | B26: 1432 | C26: 1521 | D26: 1621 | E26: 1725 | F26: 1827 | G26: 1932 | H26: 2043 | I26: 2160 | J26: 2261 | K26: 2363 | L26: 2465 | M26: 2569 | N26: 9147 | O26: 20965
A28: Addendum:
A29: Outlays adjusted to exclude timing shifts
A30: Mandatory outlays | B30: 4168 | C30: 4529 | D30: 4783 | E30: 4887 | F30: 5185 | G30: 5375 | H30: 5582 | I30: 5835 | J30: 6117 | K30: 6425 | L30: 6716 | M30: 7028 | N30: 25812 | O30: 57933
A31: Discretionary outlays | B31: 1872 | C31: 1880 | D31: 1882 | E31: 1923 | F31: 1954 | G31: 1989 | H31: 2024 | I31: 2063 | J31: 2105 | K31: 2147 | L31: 2194 | M31: 2244 | N31: 9772 | O31: 20524
A32: Total outlays | B32: 7010 | C32: 7449 | D32: 7772 | E32: 8028 | F32: 8463 | G32: 8796 | H32: 9155 | I32: 9569 | J32: 10006 | K32: 10475 | L32: 10929 | M32: 11416 | N32: 42214 | O32: 94610
A34: Gross domestic product | B34: 30362 | C34: 31902 | D34: 33315 | E34: 34666 | F34: 36010 | G34: 37391 | H34: 38813 | I34: 40277 | J34: 41796 | K34: 43373 | L34: 45012 | M34: 46712 | N34: 180195 | O34: 397364
B36: =B14/B34 -> 0.0366906 | C36: =C14/C34 -> 0.040154222 | D36: =D14/D34 -> 0.039831908 | E36: =E14/E34 -> 0.037039174 | F36: =F14/F34 -> 0.036823105 | G36: =G14/G34 -> 0.036666578 | H36: =H14/H34 -> 0.035477804 | I36: =I14/I34 -> 0.034759292 | ... M36: =M14/M34 -> 0.033289091
B37: =SUM(B14:B15)/B34 -> 0.024504315 | C37: =SUM(C14:C15)/C34 -> 0.027239671 | D37: =SUM(D14:D15)/D34 -> 0.027435089 | E37: =SUM(E14:E15)/E34 -> 0.024519702 | F37: =SUM(F14:F15)/F34 -> 0.023993335 | G37: =SUM(G14:G15)/G34 -> 0.023187398 | H37: =SUM(H14:H15)/H34 -> 0.021539175 | I37: =SUM(I14:I15)/I34 -> 0.020756263 | ... M37: =SUM(M14:M15)/M34 -> 0.018838842
C38: =(C14-B14)/B14 -> 0.14991023 | D38: =(D14-C14)/C14 -> 0.035909446 | E38: =(E14-D14)/D14 -> -0.032403919 | F38: =(F14-E14)/E14 -> 0.03271028 | G38: =(G14-F14)/F14 -> 0.033936652 | H38: =(H14-G14)/G14 -> 0.0043763676 | I38: =(I14-H14)/H14 -> 0.016702977 | J38: =(J14-I14)/I14 -> 0.047142857 | ... M38: =(M14-L14)/L14 -> 0.066529492
C39: =(C15-B15)/B15 -> 0.11351351 | D39: =(D15-C15)/C15 -> 0.0024271845 | E39: =(E15-D15)/D15 -> 0.050847458 | F39: =(F15-E15)/E15 -> 0.064516129 | G39: =(G15-F15)/F15 -> 0.090909091 | H39: =(H15-G15)/G15 -> 0.073412698 | I39: =(I15-H15)/H15 -> 0.042513863 | J39: =(J15-I15)/I15 -> 0.04787234 | ... M39: =(M15-L15)/L15 -> 0.051401869
F40: =GEOMEAN(C39:M39) -> 0.043704917
B69: Average 2011 - 2024 | C69: 0.042
B70: 2025 | C70: =B37 -> 0.024504315
B71: 2026 | C71: =C37 -> 0.027239671
B72: 2036 | C72: =M37 -> 0.018838842

Sheet Social Security
A2: SECTION 1: CURRENT BASELINE
A3: Metric | B3: Value | C3: Unit | D3: Source | E3: Notes
A4: FY2025 Social Security outlays | B4: 1647 | C4: $B | D4: CBO Baseline 2025 | E4: Up $127B (+8%) from FY2024
A5: 10-year projected OASDI shortfall (2026-2035) | B5: 2600 | C5: $B | D5: CBO / CRFB Mar 2025 | E5: Revenues fall $2.6T short of costs over next decade
A6: OASI trust fund depletion year | B6: 2033 | C6: Year | D6: 2025 Trustees Report | E6: Only 77% of scheduled benefits payable after depletion
A7: DI trust fund depletion year | B7: 2099 | C7: Year | D7: 2025 Trustees Report | E7: DI is solvent through at least 2099
A8: 2026 taxable maximum | B8: 184500 | C8: $ | D8: SSA COLA 2026 | E8: Up from $176,100 in 2025
A9: Current payroll tax rate (OASDI) | B9: 0.124 | C9: % | D9: IRC / SSA | E9: 6.2% employee + 6.2% employer
A10: Share of earnings currently taxable | B10: 0.82 | C10: % | D10: CBO 2025 | E10: 82% of covered earnings fall below the cap
A11: 75-year actuarial deficit (% of taxable payroll) | B11: 0.038 | C11: % | D11: 2025 Trustees Report | E11: Highest in nearly 50 years; nearly doubled since 2010
A12: 2026 COLA adjustment | B12: 0.028 | C12: % | D12: SSA Oct 2025 | E12: +2.8%, effective Jan 2026
A13: Payroll tax revenue (2023) | B13: 1100 | C13: $B | D13: SSA / PGPF | E13: 90% of total SS income
A15: SECTION 2: REVENUE-SIDE SOLUTIONS (TAX FIXES)
A16: Policy Option | B16: 10-Year Revenue Gain ($B) | C16: 75-Year Solvency Gap Closed | D16: Who Is Affected | E16: Key Trade-Off / Mechanism | F16: Source
A17: A. Raise taxable max to 90% of earnings (~$305,100) | B17: 800 | C17: 0.2 | D17: Top 18% of earners (above current $184,500 cap) | E17: Additional taxed earnings also increase future benefits for those earners, partially offsetting revenue gains | F17: CBO Budget Options 2024; CRFB Mar 2025
A18: B. Apply 12.4% tax on earnings > $250K ("donut hole," no benefit credit) | B18: 1600 | C18: 0.7 | D18: Top 6% of earners; gap between cap and $250K untaxed | E18: No benefit credit means pure revenue gain; most aggressive solvency fix among cap options | F18: CBO Budget Options; CRFB Mar 2025
A19: C. Eliminate the cap entirely (with benefit credit) | B19: 3200 | C19: 0.53 | D19: All earners above $184,500 (2026 cap) | E19: Largest gross revenue but future benefit obligations grow; net trust-fund gain smaller than 'no-credit' version | F19: SS Trustees; PGPF May 2025
A20: D. Eliminate the cap entirely (no benefit credit) | B20: Not separately estimated | C20: 0.73 | D20: All earners above $184,500 (2026 cap) | E20: Breaks the traditional tax-benefit link; strongest solvency effect but most politically contentious | F20: PGPF / SSA Chief Actuary
A21: E. Cover newly hired state & local government workers | B21: 180 | C21: Not separately est. | D21: 25% of state/local employees currently opted out | E21: Long-term net positive: added payroll tax now, modest benefit costs decades later | F21: CBO Budget Options; CRFB Mar 2025
A22: F. Increase covered workers via immigration | B22: 900 | C22: Not separately est. | D22: Immigrant workers entering the labor force | E22: CBO: 2021-2026 immigration surge reduces 10-year deficit by $0.9T; SS chief actuary confirms positive trust-fund effect | F22: CBO Jun 2024; BPC Dec 2025
A23: G. Raise payroll tax rate by 1 pp (to 13.4%) | B23: 1300 | C23: Not separately est. | D23: All covered workers and employers | E23: Broad-based; most regressive option since lower earners pay higher share of income in payroll tax | F23: CRFB Jul 2025 (CBO revenue options)
A25: SECTION 3: BENEFIT-SIDE FIXES (FOR CONTEXT)
A26: Policy Option | B26: 10-Year Savings ($B) | C26: 75-Year Solvency Gap Closed | D26: Notes | F26: Source
A27: Progressive indexing (Simpson-Bowles formula) | B27: 170-280 | C27: Not separately est. | D27: Slow benefit growth for higher earners; protect bottom 50% | F27: CRFB Mar 2025
A28: Switch COLA to chained CPI | B28: 260 | C28: 0.1 | D28: More accurate inflation measure; $350B if applied gov-wide | F28: CBO; CRFB Mar 2025
A29: Raise full retirement age to 70 (2 mo/yr) | B29: 150 | C29: 0.35 | D29: Reflects longer life expectancy; phased in gradually | F29: CBO; CRFB Mar 2025
A30: Tighten SSDI work-recency requirement | B30: 70 | C30: N/A | D30: From 5-of-10 years to 4-of-6 years | F30: CBO; CRFB Mar 2025
A32: SECTION 4: CONNECTION TO FEDERAL DEBT STABILIZATION
A33: Metric | B33: Value | C33: Unit | D33: Source
A34: Projected FY2026 federal deficit | B34: 1900 | C34: $B | D34: CBO 2025 Baseline
A35: Debt held by public (current, % of GDP) | B35: 1 | C35: % GDP | D35: BPC / CBO Nov 2025
A36: Projected debt in 2036 (% of GDP) | B36: 1.2 | C36: % GDP | D36: CBO Long-Term Outlook 2025
A37: 10-year SS shortfall if no action | B37: 2600 | C37: $B | D37: CBO 2025
A38: Benefit cut at OASI depletion (2033) | B38: 0.23 | C38: % | D38: 2025 Trustees Report
A40: SECTION 5: ILLUSTRATIVE POLICY COMBINATIONS
A41: Scenario | B41: Components | C41: Est. 10-Year Revenue / Savings ($B) | D41: Est. 75-Year Gap Closed | E41: Debt Stabilization Effect
A42: Moderate Revenue | B42: A (raise cap to 90%) + E (cover state/local) | C42: $980B | D42: 20-25% | E42: Reduces 10-yr SS shortfall by ~38%; modest debt-to-GDP improvement
A43: Aggressive Revenue | B43: B (donut hole $250K+) + E (cover state/local) + F (immigration) | C43: $2,680B | D43: 70%+ | E43: Nearly closes 10-yr SS shortfall; significant debt-to-GDP reduction
A44: Balanced (Revenue + Benefits) | B44: A (raise cap to 90%) + E (state/local) + chained CPI + raise retirement age | C44: $1,390B | D44: 65%+ | E44: Addresses both sides; strongest long-term solvency signal to bond markets
A45: Full Solvency Package | B45: B (donut hole $250K+) + E + chained CPI + progressive indexing | C45: $2,110-$2,220B | D45: 80%+ | E45: Near-full 75-year solvency; removes SS from debt-driver projections
A47: Note: Combined effects are approximate. CBO cautions that interactions between policies mean combined savings do not always equal the sum of individual estimates.
A48: Sources: CBO Budget Options (2024-2025), CRFB (Mar 2025), 2025 Social Security Trustees Report, PGPF (May 2025), SSA COLA (Oct 2025), BPC (Dec 2025), CBO Immigration Report (Jun 2024).

Sheet Net Interest
A1: Outlays (millions of dollars) | B1: 2026 | C1: 2027 | D1: 2028 | E1: 2029 | F1: 2030 | G1: 2031 | H1: 2032 | I1: 2033 | J1: 2034 | K1: 2035 | L1: 2036
A2: Interest on Treasury debt securities (gross) | B2: 1299635 | C2: 1362057 | D2: 1474176 | E2: 1576811 | F2: 1683578 | G2: 1798435 | H2: 1911616 | I2: 2023842 | J2: 2154446 | K2: 2280725 | L2: 2417026
A3: Others | B3: -260659 | C3: -254342 | D3: -256352 | E3: -252315 | F3: -251742 | G3: -250052 | H3: -241169 | I3: -239478 | J3: -250695 | K3: -261653 | L3: -272690
A4: Interest received by trust funds
A5: Offsetting receipts
A6: Interest on investments in public debt securities
A7: Offsets, income from donated securities
A8: Earnings on investments, perishable agricultural commodities
A9: Proprietary Transactions
A10: Earning on investments, Native American institutions endowment
A11: Subfunction 908 receipts
A12: Earnings on investments, Abandoned Mine Reclamation Fund
A13: Interest, tribal funds
A14: Natural resources damages from legal action
A15: Wildlife restoration fund
... A56: Gains and losses on non-federal securities, National railroad retirement

Sheet Actual Revenue Progression
A1: 1. CBO's Baseline Projections of Revenues
A2: Billions of Dollars
P4: Total
A5: Fiscal Year | D5: Actual, 2022 | E5: 2023 | F5: 2024 | G5: 2025 | H5: 2026F | I5: 2027F | J5: 2028F | K5: 2029F | L5: 2030F | M5: 2031F | N5: 2032F | O5: 2033F | P5: 2024– 2028 | Q5: 2024– 2055
A6: Individual Income Taxes | D6: 2632.146 | E6: 2176.481 | F6: 2426.067 | G6: 2656.044
A7: Payroll Taxes | D7: 1483.527 | E7: 1614.456 | F7: 1708.926 | G7: 1748.294
A8: Corporate Income Taxes | D8: 424.865 | E8: 419.584 | F8: 529.867 | G8: 452.089
A9: Other | G9: 194.866
B10: Excise taxes | D10: 87.728 | E10: 75.802 | F10: 101.435 | G10: 105.936
B11: Federal Reserve remittances | D11: 106.674 | E11: 0.581 | F11: 3.131 | G11: 5.49
B12: Customs duties | D12: 99.908 | E12: 80.338 | F12: 77.037 | G12: 195
B13: Estate and gift taxes | D13: 32.55 | E13: 33.668 | F13: 31.616 | G13: 29.462
B14: Miscellaneous fees and fines | D14: 30.001 | E14: 40.037 | F14: 40.025 | G14: 42
C15: Subtotal | D15: 356.861 | E15: 230 | F15: 253 | G15: 183
B16: Total | D16: 4897.399 | E16: 4440.947 | F16: 4918.104 | G16: 5234.616
C17: On-budget | D17: 3831.424 | E17: 3247.192 | F17: 3658.221 | G17: 3950.88
C18: Off-budgetᵃ | D18: 1065.975 | E18: 1193.755 | F18: 1259.883 | G18: 1283.736
A20: Memorandum:
A21: Gross Domestic Product | D21: 25015.5 | E21: 26973.775 | F21: 28823.025 | G21: 30362.025
A22: Gross Domestic Income | E22: 26569.725 | F22: 29016.6 | G22: 30101.765
D23: As a Percentage of Gross Domestic Product
A24: Individual Income Taxes | D24: 10.5 | E24: 8.069 | F24: 8.417 | G24: 8.748
A25: Payroll Taxes | D25: 5.9 | E25: 5.985 | F25: 5.929 | G25: 5.758
A26: Corporate Income Taxes | D26: 1.7 | E26: 1.556 | F26: 1.838 | G26: 1.489
A27: Other | G27: 0.642
B28: Excise taxes | D28: 0.4 | E28: 0.281 | F28: 0.352 | G28: 0.349
B29: Federal Reserve remittances | D29: 0.4 | E29: 0.002 | F29: 0.011 | G29: 0.018
B30: Customs duties | D30: 0.4 | E30: 0.298 | F30: 0.267 | G30: 0.6
B31: Estate and gift taxes | D31: 0.1 | E31: 0.125 | F31: 0.11 | G31: 0.097
B32: Miscellaneous fees and fines | D32: 0.1 | E32: 0.148 | F32: 0.139 | G32: 0.1
C33: Subtotal | D33: 1.4 | E33: 0.9 | F33: 0.9 | G33: 0.6
B34: Total | D34: 19.6 | E34: 16.464 | F34: 17.063 | G34: 17.241
C35: On-budget | D35: 15.3 | E35: 12.038 | F35: 12.692 | G35: 13.013
C36: Off-budgetᵃ | D36: 4.3 | E36: 4.426 | F36: 4.371 | G36: 4.228
A38: Data source: Congressional Budget Office.
A40: a. Receipts from Social Security payroll taxes.
A48: 1. CBO's Baseline Projections of Revenues
A49: Billions of Dollars
P51: Total
A52: Fiscal Year | D52: Actual, 2022 | E52: 2023 | F52: 2024 | G52: 2025 | H52: 2026 | I52: 2027 | J52: 2028 | K52: 2029 | L52: 2030 | M52: 2031 | N52: 2032 | O52: 2033 | P52: 2024– 2028 | Q52: 2024– 2033
A53: Individual Income Taxes | D53: 2632.146 | E53: 2524.85 | F53: 2474.638 | G53: 2516.848 | H53: 2768.291 | I53: 3018.96 | J53: 3122.78 | K53: 3247.703 | L53: 3379.645 | M53: 3517.479 | N53: 3652.27 | O53: 3806.261 | P53: 13901.517 | Q53: 31504.875
A54: Payroll Taxes | D54: 1483.527 | E54: 1562.308 | F54: 1632.919 | G54: 1702.795 | H54: 1778.408 | I54: 1849.482 | J54: 1920.416 | K54: 1993.216 | L54: 2068.162 | M54: 2146.652 | N54: 2226.168 | O54: 2306.533 | P54: 8884.02 | Q54: 19624.751
A55: Corporate Income Taxes | D55: 424.865 | E55: 475.38 | F55: 478.517 | G55: 488.591 | H55: 494.542 | I55: 494.277 | J55: 505.666 | K55: 514.1 | L55: 520.36 | M55: 526.912 | N55: 527.173 | O55: 539.307 | P55: 2461.593 | Q55: 5089.445
A56: Other
B57: Excise taxes | D57: 87.728 | E57: 90.506 | F57: 101.1 | G57: 100.248 | H57: 100.895 | I57: 101.644 | J57: 102.527 | K57: 103.309 | L57: 104.264 | M57: 105.216 | N57: 106.279 | O57: 107.27 | P57: 506.414 | Q57: 1032.752
B58: Federal Reserve remittances | D58: 106.674 | E58: 0.908 | F58: 3.561 | G58: 6.039 | H58: 7.469 | I58: 9.925 | J58: 77.885 | K58: 87.552 | L58: 98.195 | M58: 109.21 | N58: 122.462 | O58: 129.751 | P58: 104.879 | Q58: 652.049
B59: Customs duties | D59: 99.908 | E59: 98.747 | F59: 96.874 | G59: 98.478 | H59: 101 | I59: 102.789 | J59: 104.211 | K59: 105.222 | L59: 106.221 | M59: 107.367 | N59: 108.505 | O59: 109.639 | P59: 503.352 | Q59: 1040.306
B60: Estate and gift taxes | D60: 32.55 | E60: 26.509 | F60: 24.765 | G60: 24.362 | H60: 25.985 | I60: 38.619 | J60: 41.993 | K60: 44.24 | L60: 46.763 | M60: 49.584 | N60: 53.131 | O60: 56.784 | P60: 155.724 | Q60: 406.226
B61: Miscellaneous fees and fines | D61: 30.001 | E61: 35.502 | F61: 35.132 | G61: 37.1 | H61: 40.279 | I61: 42.395 | J61: 43.782 | K61: 46.91 | L61: 44.172 | M61: 44.41 | N61: 45.438 | O61: 46.722 | P61: 198.688 | Q61: 426.34
C62: Subtotal | D62: 356.861 | E62: 252.172 | F62: 261.432 | G62: 266.227 | H62: 275.628 | I62: 295.372 | J62: 370.398 | K62: 387.233 | L62: 399.615 | M62: 415.787 | N62: 435.815 | O62: 450.166 | P62: 1469.057 | Q62: 3557.673
B63: Total | D63: 4897.399 | E63: 4814.71 | F63: 4847.506 | G63: 4974.461 | H63: 5316.869 | I63: 5658.091 | J63: 5919.26 | K63: 6142.252 | L63: 6367.782 | M63: 6606.83 | N63: 6841.426 | O63: 7102.267 | P63: 26716.187 | Q63: 59776.744
C64: On-budget | D64: 3831.424 | E64: 3681.471 | F64: 3651.961 | G64: 3719.008 | H64: 4005.654 | I64: 4295.086 | J64: 4504.21 | K64: 4674.208 | L64: 4845.549 | M64: 5027.261 | N64: 5204.11 | O64: 5406.915 | P64: 20175.919 | Q64: 45333.962
C65: Off-budgetᵃ | D65: 1065.975 | E65: 1133.239 | F65: 1195.545 | G65: 1255.453 | H65: 1311.215 | I65: 1363.005 | J65: 1415.05 | K65: 1468.044 | L65: 1522.233 | M65: 1579.569 | N65: 1637.316 | O65: 1695.352 | P65: 6540.268 | Q65: 14442.782
A67: Memorandum:
A68: Gross Domestic Product | D68: 25015.5 | E68: 26237.92 | F68: 27266.205 | G68: 28610.078 | H68: 29932.298 | I68: 31251.275 | J68: 32525.38 | K68: 33810.782 | L68: 35132.682 | M68: 36487.812 | N68: 37874.165 | O68: 39288.07 | P68: 149585.24 | Q68: 332178.75
D70: As a Percentage of Gross Domestic Product
A71: Individual Income Taxes | D71: 10.5 | E71: 9.6 | F71: 9.1 | G71: 8.8 | H71: 9.2 | I71: 9.7 | J71: 9.6 | K71: 9.6 | L71: 9.6 | M71: 9.6 | N71: 9.6 | O71: 9.7 | P71: 9.3 | Q71: 9.5
A72: Payroll Taxes | D72: 5.9 | E72: 6 | F72: 6 | G72: 6 | H72: 5.9 | I72: 5.9 | J72: 5.9 | K72: 5.9 | L72: 5.9 | M72: 5.9 | N72: 5.9 | O72: 5.9 | P72: 5.9 | Q72: 5.9
A73: Corporate Income Taxes | D73: 1.7 | E73: 1.8 | F73: 1.8 | G73: 1.7 | H73: 1.7 | I73: 1.6 | J73: 1.6 | K73: 1.5 | L73: 1.5 | M73: 1.4 | N73: 1.4 | O73: 1.4 | P73: 1.6 | Q73: 1.5
A74: Other
B75: Excise taxes | D75: 0.4 | E75: 0.3 | F75: 0.4 | G75: 0.4 | H75: 0.3 | I75: 0.3 | J75: 0.3 | K75: 0.3 | L75: 0.3 | M75: 0.3 | N75: 0.3 | O75: 0.3 | P75: 0.3 | Q75: 0.3
B76: Federal Reserve remittances | D76: 0.4 | E76: 0 | F76: 0 | G76: 0 | H76: 0 | I76: 0 | J76: 0.2 | K76: 0.3 | L76: 0.3 | M76: 0.3 | N76: 0.3 | O76: 0.3 | P76: 0.1 | Q76: 0.2
B77: Customs duties | D77: 0.4 | E77: 0.4 | F77: 0.4 | G77: 0.3 | H77: 0.3 | I77: 0.3 | J77: 0.3 | K77: 0.3 | L77: 0.3 | M77: 0.3 | N77: 0.3 | O77: 0.3 | P77: 0.3 | Q77: 0.3
B78: Estate and gift taxes | D78: 0.1 | E78: 0.1 | F78: 0.1 | G78: 0.1 | H78: 0.1 | I78: 0.1 | J78: 0.1 | K78: 0.1 | L78: 0.1 | M78: 0.1 | N78: 0.1 | O78: 0.1 | P78: 0.1 | Q78: 0.1
B79: Miscellaneous fees and fines | D79: 0.1 | E79: 0.1 | F79: 0.1 | G79: 0.1 | H79: 0.1 | I79: 0.1 | J79: 0.1 | K79: 0.1 | L79: 0.1 | M79: 0.1 | N79: 0.1 | O79: 0.1 | P79: 0.1 | Q79: 0.1
C80: Subtotal | D80: 1.4 | E80: 1 | F80: 1 | G80: 0.9 | H80: 0.9 | I80: 0.9 | J80: 1.1 | K80: 1.1 | L80: 1.1 | M80: 1.1 | N80: 1.2 | O80: 1.1 | P80: 1 | Q80: 1.1
B81: Total | D81: 19.6 | E81: 18.4 | F81: 17.8 | G81: 17.4 | H81: 17.8 | I81: 18.1 | J81: 18.2 | K81: 18.2 | L81: 18.1 | M81: 18.1 | N81: 18.1 | O81: 18.1 | P81: 17.9 | Q81: 18
C82: On-budget | D82: 15.3 | E82: 14 | F82: 13.4 | G82: 13 | H82: 13.4 | I82: 13.7 | J82: 13.8 | K82: 13.8 | L82: 13.8 | M82: 13.8 | N82: 13.7 | O82: 13.8 | P82: 13.5 | Q82: 13.6
C83: Off-budgetᵃ | D83: 4.3 | E83: 4.3 | F83: 4.4 | G83: 4.4 | H83: 4.4 | I83: 4.4 | J83: 4.4 | K83: 4.3 | L83: 4.3 | M83: 4.3 | N83: 4.3 | O83: 4.3 | P83: 4.4 | Q83: 4.3
A85: Data source: Congressional Budget Office.
A87: a. Receipts from Social Security payroll taxes.
A91: 1. CBO's Baseline Projections of Revenues
A92: Billions of dollars
N94: Total
A95: Fiscal year | B95: Actual, 2023 | C95: 2024 | D95: 2025 | E95: 2026 | F95: 2027 | G95: 2028 | H95: 2029 | I95: 2030 | J95: 2031 | K95: 2032 | L95: 2033 | M95: 2034 | N95: 2025– 2029 | O95: 2025– 2034
A96: Individual income taxes | B96: 2176.481 | C96: 2446.664 | D96: 2549.865 | E96: 2841.002 | F96: 3121.953 | G96: 3224.15 | H96: 3326.854 | I96: 3455.086 | J96: 3583.2 | K96: 3710.438 | L96: 3858.924 | M96: 4020.648 | N96: 15063.824 | O96: 33692.12
A97: Payroll taxes | B97: 1614.456 | C97: 1678.453 | D97: 1737.193 | E97: 1814.246 | F97: 1885.543 | G97: 1960.072 | H97: 2038.246 | I97: 2118.127 | J97: 2199.983 | K97: 2283.177 | L97: 2367.911 | M97: 2455.084 | N97: 9435.3 | O97: 20859.582
A98: Corporate income taxes | B98: 419.584 | C98: 525.402 | D98: 490.086 | E98: 470.452 | F98: 459.399 | G98: 461.554 | H98: 460.858 | I98: 462.811 | J98: 465.987 | K98: 471.01 | L98: 495.304 | M98: 506.704 | N98: 2342.349 | O98: 4744.165
A99: Other
A100: Excise taxes | B100: 75.802 | C100: 89.162 | D100: 96.433 | E100: 98.984 | F100: 99.646 | G100: 99.664 | H100: 99.604 | I100: 99.308 | J100: 98.682 | K100: 97.385 | L100: 97.613 | M100: 98.285 | N100: 494.331 | O100: 985.604
A101: Federal Reserve remittances | B101: 0.581 | C101: 2.191 | D101: 4.467 | E101: 6.669 | F101: 8.388 | G101: 10.55 | H101: 13.268 | I101: 22.075 | J101: 111.232 | K101: 128.474 | L101: 139.901 | M101: 153.418 | N101: 43.342 | O101: 598.442
A102: Customs duties | B102: 80.338 | C102: 73.379 | D102: 76.187 | E102: 79.779 | F102: 83.017 | G102: 85.427 | H102: 87.107 | I102: 88.577 | J102: 90.273 | K102: 92.085 | L102: 94.008 | M102: 96.026 | N102: 411.517 | O102: 872.486
A103: Estate and gift taxes | B103: 33.668 | C103: 32.367 | D103: 34.589 | E103: 35.429 | F103: 49.449 | G103: 52.664 | H103: 54.73 | I103: 57.313 | J103: 60.416 | K103: 63.972 | L103: 67.914 | M103: 72.174 | N103: 226.861 | O103: 548.65
A104: Miscellaneous fees and fines | B104: 40.037 | C104: 42.143 | D104: 48.808 | E104: 47.039 | F104: 48.701 | G104: 49.805 | H104: 52.758 | I104: 50.715 | J104: 51.355 | K104: 52.855 | L104: 54.441 | M104: 56.391 | N104: 247.111 | O104: 512.868
A105: Subtotal | B105: 230.426 | C105: 239.242 | D105: 260.484 | E105: 267.9 | F105: 289.201 | G105: 298.11 | H105: 307.467 | I105: 317.988 | J105: 411.958 | K105: 434.771 | L105: 453.877 | M105: 476.294 | N105: 1423.162 | O105: 3518.05
B106: _____ | C106: _____ | D106: _____ | E106: _____ | F106: _____ | G106: _____ | H106: _____ | I106: _____ | J106: _____ | K106: _____ | L106: _____ | M106: _____ | N106: ______ | O106: ______
A107: Total | B107: 4440.947 | C107: 4889.761 | D107: 5037.628 | E107: 5393.6 | F107: 5756.096 | G107: 5943.886 | H107: 6133.425 | I107: 6354.012 | J107: 6661.128 | K107: 6899.396 | L107: 7176.016 | M107: 7458.73 | N107: 28264.635 | O107: 62813.917
A108: On-budget | B108: 3247.192 | C108: 3651.681 | D108: 3751.008 | E108: 4052.877 | F108: 4365.167 | G108: 4500.675 | H108: 4635.385 | I108: 4799.347 | J108: 5047.893 | K108: 5226.529 | L108: 5442.436 | M108: 5662.382 | N108: 21305.112 | O108: 47483.699
A109: Off-budgetᵃ | B109: 1193.755 | C109: 1238.08 | D109: 1286.62 | E109: 1340.723 | F109: 1390.929 | G109: 1443.211 | H109: 1498.04 | I109: 1554.665 | J109: 1613.235 | K109: 1672.867 | L109: 1733.58 | M109: 1796.348 | N109: 6959.523 | O109: 15330.218
A111: Addendum:
A112: Gross domestic product | B112: 26973.775 | C112: 28467.238 | D112: 29710.66 | E112: 30856.308 | F112: 31971.678 | G112: 33115.13 | H112: 34345.763 | I112: 35653.953 | J112: 37018.255 | K112: 38431.568 | L112: 39890.39 | M112: 41397.94 | N112: 159999.54 | O112: 352391.64
A113: Gross domestic income | B113: 26569.725 | C113: 27991.819 | D113: 29541.011 | E113: 30811.627 | F113: 31970.965 | G113: 33130.175 | H113: 34366.839 | I113: 35677.731 | J113: 37043.602 | K113: 38458.111 | L113: 39918.02 | M113: 41426.642 | N113: 159820.62 | O113: 352344.72
B115: As a percentage of gross domestic product
A116: Individual income taxes | B116: 8.069 | C116: 8.595 | D116: 8.582 | E116: 9.207 | F116: 9.765 | G116: 9.736 | H116: 9.686 | I116: 9.691 | J116: 9.68 | K116: 9.655 | L116: 9.674 | M116: 9.712 | N116: 9.415 | O116: 9.561
A117: Payroll taxes | B117: 5.985 | C117: 5.896 | D117: 5.847 | E117: 5.88 | F117: 5.898 | G117: 5.919 | H117: 5.934 | I117: 5.941 | J117: 5.943 | K117: 5.941 | L117: 5.936 | M117: 5.93 | N117: 5.897 | O117: 5.919
A118: Corporate income taxes | B118: 1.556 | C118: 1.846 | D118: 1.65 | E118: 1.525 | F118: 1.437 | G118: 1.394 | H118: 1.342 | I118: 1.298 | J118: 1.259 | K118: 1.226 | L118: 1.242 | M118: 1.224 | N118: 1.464 | O118: 1.346
A119: Other
A120: Excise taxes | B120: 0.281 | C120: 0.313 | D120: 0.325 | E120: 0.321 | F120: 0.312 | G120: 0.301 | H120: 0.29 | I120: 0.279 | J120: 0.267 | K120: 0.253 | L120: 0.245 | M120: 0.237 | N120: 0.309 | O120: 0.28
A121: Federal Reserve remittances | B121: 0.002 | C121: 0.008 | D121: 0.015 | E121: 0.022 | F121: 0.026 | G121: 0.032 | H121: 0.039 | I121: 0.062 | J121: 0.3 | K121: 0.334 | L121: 0.351 | M121: 0.371 | N121: 0.027 | O121: 0.17
A122: Customs duties | B122: 0.298 | C122: 0.258 | D122: 0.256 | E122: 0.259 | F122: 0.26 | G122: 0.258 | H122: 0.254 | I122: 0.248 | J122: 0.244 | K122: 0.24 | L122: 0.236 | M122: 0.232 | N122: 0.257 | O122: 0.248
...
